{
  "metadata": {
    "collection_date": "2026-01-11T17:54:02.822838",
    "repository": "https://github.com/skypjack/entt",
    "repository_name": "skypjack/entt"
  },
  "commit_info": {
    "old_sha": "c777cda8577a3e1e1384d86c44a498a83e6e45ae",
    "new_sha": "ff8544f97dcc41888699afaf7852e486540c6e99",
    "commit_message": [
      "sparse set: simplify try_emplace iterator computation to improve MSVC codegen (#1286)"
    ],
    "commit_date": "2025-09-26T09:20:58+00:00",
    "patch": [
      "--- src/entt/entity/sparse_set.hpp\n@@ -375,7 +375,7 @@ class basic_sparse_set {\n             break;\n         }\n \n-        return --(end() - static_cast<difference_type>(pos));\n+    \treturn iterator(packed, static_cast<difference_type>(pos) + 1);\n     }\n \n     /*! @brief Forwards variables to derived classes, if any. */"
    ],
    "files_changed": [
      {
        "filename": "src/entt/entity/sparse_set.hpp",
        "status": "modified",
        "additions": 1,
        "deletions": 1,
        "changes": 2,
        "patch": "@@ -375,7 +375,7 @@ class basic_sparse_set {\n             break;\n         }\n \n-        return --(end() - static_cast<difference_type>(pos));\n+    \treturn iterator(packed, static_cast<difference_type>(pos) + 1);\n     }\n \n     /*! @brief Forwards variables to derived classes, if any. */"
      }
    ],
    "lines_added": 1,
    "lines_removed": 1
  },
  "issues": [],
  "pull_requests": [],
  "build_info": {
    "old_build_script": "#!/bin/bash\n#!/bin/bash\ncmake -S /test_workspace/workspace/old -B /test_workspace/workspace/old/build -DCMAKE_BUILD_TYPE=Debug -DCMAKE_EXPORT_COMPILE_COMMANDS=ON -DENTT_BUILD_TESTING=ON -DBUILD_TESTING=ON",
    "new_build_script": "#!/bin/bash\n#!/bin/bash\ncmake -S /test_workspace/workspace/old -B /test_workspace/workspace/old/build -DCMAKE_BUILD_TYPE=Debug -DCMAKE_EXPORT_COMPILE_COMMANDS=ON -DENTT_BUILD_TESTING=ON -DBUILD_TESTING=ON",
    "old_test_script": "#!/bin/bash\ncmake --build /test_workspace/workspace/old/build -- -j 1",
    "new_test_script": "#!/bin/bash\ncmake --build /test_workspace/workspace/old/build -- -j 1",
    "build_system": "cmake"
  },
  "performance_analysis": {
    "is_significant": false,
    "p_value": 1.0,
    "is_pair_significant": false,
    "pair_p_value": 1.0,
    "is_binom_significant": false,
    "binom_p_value": 1.0,
    "is_wilcoxon_significant": false,
    "wilcoxon_p_value": 0.9999995155658383,
    "is_mannwhitney_significant": false,
    "mannwhitney_p_value": 0.09436429028719429,
    "relative_improvement": 0.0035052578868302593,
    "absolute_improvement_ms": 2.3333333333332984,
    "old_mean_ms": 665.6666666666669,
    "new_mean_ms": 663.3333333333336,
    "old_std_ms": 6.260623155792931,
    "new_std_ms": 5.466722735905344,
    "effect_size_cohens_d": 0.3970216349158215,
    "old_ci95_ms": [
      663.3289115603638,
      668.0044217729699
    ],
    "new_ci95_ms": [
      661.2920255157915,
      665.3746411508756
    ],
    "old_ci99_ms": [
      662.516039916251,
      668.8172934170827
    ],
    "new_ci99_ms": [
      660.5822329300274,
      666.0844337366398
    ],
    "new_times_s": [
      0.67,
      0.67,
      0.66,
      0.67,
      0.66,
      0.66,
      0.66,
      0.65,
      0.66,
      0.66,
      0.67,
      0.66,
      0.66,
      0.67,
      0.66,
      0.66,
      0.67,
      0.67,
      0.66,
      0.67,
      0.67,
      0.66,
      0.66,
      0.66,
      0.67,
      0.67,
      0.67,
      0.66,
      0.66,
      0.66,
      0.66
    ],
    "old_times_s": [
      0.67,
      0.68,
      0.68,
      0.67,
      0.66,
      0.66,
      0.66,
      0.67,
      0.66,
      0.67,
      0.67,
      0.67,
      0.66,
      0.67,
      0.67,
      0.66,
      0.66,
      0.66,
      0.67,
      0.67,
      0.67,
      0.66,
      0.66,
      0.66,
      0.66,
      0.66,
      0.67,
      0.66,
      0.66,
      0.67,
      0.67
    ]
  },
  "tests": {
    "total_tests": 25,
    "significant_improvements": 0,
    "significant_improvements_tests": [],
    "significant_regressions": 0,
    "significant_regressions_tests": [],
    "significant_pair_improvements": 0,
    "significant_pair_improvements_tests": [],
    "significant_pair_regressions": 0,
    "significant_pair_regressions_tests": [],
    "significant_binom_improvements": 0,
    "significant_binom_improvements_tests": [],
    "significant_binom_regressions": 0,
    "significant_binom_regressions_tests": [],
    "significant_wilcoxon_improvements": 0,
    "significant_wilcoxon_improvements_tests": [],
    "significant_wilcoxon_regressions": 0,
    "significant_wilcoxon_regressions_tests": [],
    "significant_mannwhitney_improvements": 0,
    "significant_mannwhitney_improvements_tests": [],
    "significant_mannwhitney_regressions": 0,
    "significant_mannwhitney_regressions_tests": [],
    "tests": [
      {
        "test_name": "dense_map",
        "is_significant": false,
        "p_value": 0.698593320008648,
        "is_pair_significant": false,
        "pair_p_value": 0.68950897814047,
        "is_binom_significant": false,
        "binom_p_value": 0.9999999981373549,
        "is_wilcoxon_significant": false,
        "wilcoxon_p_value": 0.9999978486102682,
        "is_mannwhitney_significant": false,
        "mannwhitney_p_value": 0.16714290224817413,
        "relative_improvement": 0.03333333333333337,
        "absolute_improvement_ms": 0.3448275862068962,
        "old_mean_ms": 10.344827586206899,
        "new_mean_ms": 10.000000000000002,
        "old_std_ms": 1.8569533817705184,
        "new_std_ms": 1.7654289301252243e-15,
        "effect_size_cohens_d": 0.26261286571944487,
        "old_ci95_ms": [
          9.638480295932675,
          11.05117487648112
        ],
        "new_ci95_ms": [
          10.000000000000002,
          10.000000000000002
        ],
        "old_ci99_ms": [
          9.391978463634118,
          11.29767670877968
        ],
        "new_ci99_ms": [
          10.0,
          10.000000000000004
        ],
        "new_times": [
          0.01,
          0.01,
          0.01,
          0.01,
          0.01,
          0.01,
          0.01,
          0.01,
          0.01,
          0.01,
          0.01,
          0.01,
          0.01,
          0.01,
          0.01,
          0.01,
          0.01,
          0.01,
          0.01,
          0.01,
          0.01,
          0.01,
          0.01,
          0.01,
          0.01,
          0.01,
          0.01,
          0.01,
          0.01
        ],
        "old_times": [
          0.02,
          0.01,
          0.01,
          0.01,
          0.01,
          0.01,
          0.01,
          0.01,
          0.01,
          0.01,
          0.01,
          0.01,
          0.01,
          0.01,
          0.01,
          0.01,
          0.01,
          0.01,
          0.01,
          0.01,
          0.01,
          0.01,
          0.01,
          0.01,
          0.01,
          0.01,
          0.01,
          0.01,
          0.01
        ]
      },
      {
        "test_name": "table",
        "is_significant": false,
        "p_value": 1.0,
        "is_pair_significant": false,
        "pair_p_value": 1.0,
        "is_binom_significant": false,
        "binom_p_value": 1.0,
        "is_wilcoxon_significant": false,
        "wilcoxon_p_value": 0.9999999638108507,
        "is_mannwhitney_significant": false,
        "mannwhitney_p_value": 1.0,
        "relative_improvement": 0.0,
        "absolute_improvement_ms": 0.0,
        "old_mean_ms": 20.000000000000004,
        "new_mean_ms": 20.000000000000004,
        "old_std_ms": 3.5308578602504487e-15,
        "new_std_ms": 3.5308578602504487e-15,
        "effect_size_cohens_d": 0.0,
        "old_ci95_ms": [
          20.000000000000004,
          20.000000000000004
        ],
        "new_ci95_ms": [
          20.000000000000004,
          20.000000000000004
        ],
        "old_ci99_ms": [
          20.0,
          20.000000000000007
        ],
        "new_ci99_ms": [
          20.0,
          20.000000000000007
        ],
        "new_times": [
          0.02,
          0.02,
          0.02,
          0.02,
          0.02,
          0.02,
          0.02,
          0.02,
          0.02,
          0.02,
          0.02,
          0.02,
          0.02,
          0.02,
          0.02,
          0.02,
          0.02,
          0.02,
          0.02,
          0.02,
          0.02,
          0.02,
          0.02,
          0.02,
          0.02,
          0.02,
          0.02,
          0.02,
          0.02
        ],
        "old_times": [
          0.02,
          0.02,
          0.02,
          0.02,
          0.02,
          0.02,
          0.02,
          0.02,
          0.02,
          0.02,
          0.02,
          0.02,
          0.02,
          0.02,
          0.02,
          0.02,
          0.02,
          0.02,
          0.02,
          0.02,
          0.02,
          0.02,
          0.02,
          0.02,
          0.02,
          0.02,
          0.02,
          0.02,
          0.02
        ]
      },
      {
        "test_name": "any",
        "is_significant": false,
        "p_value": 1.0,
        "is_pair_significant": false,
        "pair_p_value": 1.0,
        "is_binom_significant": false,
        "binom_p_value": 1.0,
        "is_wilcoxon_significant": false,
        "wilcoxon_p_value": 0.9999999638108507,
        "is_mannwhitney_significant": false,
        "mannwhitney_p_value": 1.0,
        "relative_improvement": 0.0,
        "absolute_improvement_ms": 0.0,
        "old_mean_ms": 10.000000000000002,
        "new_mean_ms": 10.000000000000002,
        "old_std_ms": 1.7654289301252243e-15,
        "new_std_ms": 1.7654289301252243e-15,
        "effect_size_cohens_d": 0.0,
        "old_ci95_ms": [
          10.000000000000002,
          10.000000000000002
        ],
        "new_ci95_ms": [
          10.000000000000002,
          10.000000000000002
        ],
        "old_ci99_ms": [
          10.0,
          10.000000000000004
        ],
        "new_ci99_ms": [
          10.0,
          10.000000000000004
        ],
        "new_times": [
          0.01,
          0.01,
          0.01,
          0.01,
          0.01,
          0.01,
          0.01,
          0.01,
          0.01,
          0.01,
          0.01,
          0.01,
          0.01,
          0.01,
          0.01,
          0.01,
          0.01,
          0.01,
          0.01,
          0.01,
          0.01,
          0.01,
          0.01,
          0.01,
          0.01,
          0.01,
          0.01,
          0.01,
          0.01
        ],
        "old_times": [
          0.01,
          0.01,
          0.01,
          0.01,
          0.01,
          0.01,
          0.01,
          0.01,
          0.01,
          0.01,
          0.01,
          0.01,
          0.01,
          0.01,
          0.01,
          0.01,
          0.01,
          0.01,
          0.01,
          0.01,
          0.01,
          0.01,
          0.01,
          0.01,
          0.01,
          0.01,
          0.01,
          0.01,
          0.01
        ]
      },
      {
        "test_name": "group",
        "is_significant": false,
        "p_value": 1.0,
        "is_pair_significant": false,
        "pair_p_value": 1.0,
        "is_binom_significant": false,
        "binom_p_value": 1.0,
        "is_wilcoxon_significant": false,
        "wilcoxon_p_value": 0.9999999638108507,
        "is_mannwhitney_significant": false,
        "mannwhitney_p_value": 1.0,
        "relative_improvement": 0.0,
        "absolute_improvement_ms": 0.0,
        "old_mean_ms": 10.000000000000002,
        "new_mean_ms": 10.000000000000002,
        "old_std_ms": 1.7654289301252243e-15,
        "new_std_ms": 1.7654289301252243e-15,
        "effect_size_cohens_d": 0.0,
        "old_ci95_ms": [
          10.000000000000002,
          10.000000000000002
        ],
        "new_ci95_ms": [
          10.000000000000002,
          10.000000000000002
        ],
        "old_ci99_ms": [
          10.0,
          10.000000000000004
        ],
        "new_ci99_ms": [
          10.0,
          10.000000000000004
        ],
        "new_times": [
          0.01,
          0.01,
          0.01,
          0.01,
          0.01,
          0.01,
          0.01,
          0.01,
          0.01,
          0.01,
          0.01,
          0.01,
          0.01,
          0.01,
          0.01,
          0.01,
          0.01,
          0.01,
          0.01,
          0.01,
          0.01,
          0.01,
          0.01,
          0.01,
          0.01,
          0.01,
          0.01,
          0.01,
          0.01
        ],
        "old_times": [
          0.01,
          0.01,
          0.01,
          0.01,
          0.01,
          0.01,
          0.01,
          0.01,
          0.01,
          0.01,
          0.01,
          0.01,
          0.01,
          0.01,
          0.01,
          0.01,
          0.01,
          0.01,
          0.01,
          0.01,
          0.01,
          0.01,
          0.01,
          0.01,
          0.01,
          0.01,
          0.01,
          0.01,
          0.01
        ]
      },
      {
        "test_name": "handle",
        "is_significant": false,
        "p_value": 1.0,
        "is_pair_significant": false,
        "pair_p_value": 1.0,
        "is_binom_significant": false,
        "binom_p_value": 1.0,
        "is_wilcoxon_significant": false,
        "wilcoxon_p_value": 0.9999999638108507,
        "is_mannwhitney_significant": false,
        "mannwhitney_p_value": 1.0,
        "relative_improvement": 0.0,
        "absolute_improvement_ms": 0.0,
        "old_mean_ms": 40.00000000000001,
        "new_mean_ms": 40.00000000000001,
        "old_std_ms": 7.061715720500897e-15,
        "new_std_ms": 7.061715720500897e-15,
        "effect_size_cohens_d": 0.0,
        "old_ci95_ms": [
          40.00000000000001,
          40.00000000000001
        ],
        "new_ci95_ms": [
          40.00000000000001,
          40.00000000000001
        ],
        "old_ci99_ms": [
          40.0,
          40.000000000000014
        ],
        "new_ci99_ms": [
          40.0,
          40.000000000000014
        ],
        "new_times": [
          0.04,
          0.04,
          0.04,
          0.04,
          0.04,
          0.04,
          0.04,
          0.04,
          0.04,
          0.04,
          0.04,
          0.04,
          0.04,
          0.04,
          0.04,
          0.04,
          0.04,
          0.04,
          0.04,
          0.04,
          0.04,
          0.04,
          0.04,
          0.04,
          0.04,
          0.04,
          0.04,
          0.04,
          0.04
        ],
        "old_times": [
          0.04,
          0.04,
          0.04,
          0.04,
          0.04,
          0.04,
          0.04,
          0.04,
          0.04,
          0.04,
          0.04,
          0.04,
          0.04,
          0.04,
          0.04,
          0.04,
          0.04,
          0.04,
          0.04,
          0.04,
          0.04,
          0.04,
          0.04,
          0.04,
          0.04,
          0.04,
          0.04,
          0.04,
          0.04
        ]
      },
      {
        "test_name": "reactive_mixin",
        "is_significant": false,
        "p_value": 0.9999760418479817,
        "is_pair_significant": false,
        "pair_p_value": 0.9999760418479817,
        "is_binom_significant": false,
        "binom_p_value": 0.9999999981373549,
        "is_wilcoxon_significant": false,
        "wilcoxon_p_value": 0.9999978486102682,
        "is_mannwhitney_significant": false,
        "mannwhitney_p_value": 0.16714290224817413,
        "relative_improvement": 0.008620689655172422,
        "absolute_improvement_ms": 0.3448275862069014,
        "old_mean_ms": 40.00000000000001,
        "new_mean_ms": 39.6551724137931,
        "old_std_ms": 7.061715720500897e-15,
        "new_std_ms": 1.8569533817705188,
        "effect_size_cohens_d": 0.2626128657194488,
        "old_ci95_ms": [
          40.00000000000001,
          40.00000000000001
        ],
        "new_ci95_ms": [
          38.94882512351888,
          40.361519704067334
        ],
        "old_ci99_ms": [
          40.0,
          40.000000000000014
        ],
        "new_ci99_ms": [
          38.702323291220324,
          40.60802153636589
        ],
        "new_times": [
          0.04,
          0.04,
          0.04,
          0.04,
          0.04,
          0.03,
          0.04,
          0.04,
          0.04,
          0.04,
          0.04,
          0.04,
          0.04,
          0.04,
          0.04,
          0.04,
          0.04,
          0.04,
          0.04,
          0.04,
          0.04,
          0.04,
          0.04,
          0.04,
          0.04,
          0.04,
          0.04,
          0.04,
          0.04
        ],
        "old_times": [
          0.04,
          0.04,
          0.04,
          0.04,
          0.04,
          0.04,
          0.04,
          0.04,
          0.04,
          0.04,
          0.04,
          0.04,
          0.04,
          0.04,
          0.04,
          0.04,
          0.04,
          0.04,
          0.04,
          0.04,
          0.04,
          0.04,
          0.04,
          0.04,
          0.04,
          0.04,
          0.04,
          0.04,
          0.04
        ]
      },
      {
        "test_name": "registry",
        "is_significant": false,
        "p_value": 0.9270031011353217,
        "is_pair_significant": false,
        "pair_p_value": 0.9074878197653803,
        "is_binom_significant": false,
        "binom_p_value": 0.995934970676899,
        "is_wilcoxon_significant": false,
        "wilcoxon_p_value": 0.9369476257144758,
        "is_mannwhitney_significant": false,
        "mannwhitney_p_value": 0.3968499325647312,
        "relative_improvement": 0.007874015748031503,
        "absolute_improvement_ms": 0.34482758620689447,
        "old_mean_ms": 43.793103448275865,
        "new_mean_ms": 43.448275862068975,
        "old_std_ms": 4.938039737912402,
        "new_std_ms": 4.837252813149747,
        "effect_size_cohens_d": 0.07054709772060441,
        "old_ci95_ms": [
          41.91477358691164,
          45.67143330964009
        ],
        "new_ci95_ms": [
          41.60828329656798,
          45.28826842756997
        ],
        "old_ci99_ms": [
          41.25927202434794,
          46.326934872203786
        ],
        "new_ci99_ms": [
          40.96616072448926,
          45.930390999648694
        ],
        "new_times": [
          0.04,
          0.05,
          0.04,
          0.04,
          0.05,
          0.04,
          0.04,
          0.04,
          0.05,
          0.04,
          0.04,
          0.05,
          0.05,
          0.04,
          0.05,
          0.05,
          0.04,
          0.05,
          0.04,
          0.04,
          0.04,
          0.04,
          0.04,
          0.05,
          0.04,
          0.05,
          0.04,
          0.04,
          0.04
        ],
        "old_times": [
          0.05,
          0.05,
          0.05,
          0.04,
          0.04,
          0.05,
          0.04,
          0.04,
          0.05,
          0.05,
          0.04,
          0.05,
          0.04,
          0.04,
          0.04,
          0.04,
          0.05,
          0.04,
          0.05,
          0.04,
          0.04,
          0.04,
          0.04,
          0.04,
          0.04,
          0.04,
          0.04,
          0.05,
          0.05
        ]
      },
      {
        "test_name": "sigh_mixin",
        "is_significant": false,
        "p_value": 1.0,
        "is_pair_significant": false,
        "pair_p_value": 1.0,
        "is_binom_significant": false,
        "binom_p_value": 1.0,
        "is_wilcoxon_significant": false,
        "wilcoxon_p_value": 0.9999999638108507,
        "is_mannwhitney_significant": false,
        "mannwhitney_p_value": 1.0,
        "relative_improvement": 0.0,
        "absolute_improvement_ms": 0.0,
        "old_mean_ms": 20.000000000000004,
        "new_mean_ms": 20.000000000000004,
        "old_std_ms": 3.5308578602504487e-15,
        "new_std_ms": 3.5308578602504487e-15,
        "effect_size_cohens_d": 0.0,
        "old_ci95_ms": [
          20.000000000000004,
          20.000000000000004
        ],
        "new_ci95_ms": [
          20.000000000000004,
          20.000000000000004
        ],
        "old_ci99_ms": [
          20.0,
          20.000000000000007
        ],
        "new_ci99_ms": [
          20.0,
          20.000000000000007
        ],
        "new_times": [
          0.02,
          0.02,
          0.02,
          0.02,
          0.02,
          0.02,
          0.02,
          0.02,
          0.02,
          0.02,
          0.02,
          0.02,
          0.02,
          0.02,
          0.02,
          0.02,
          0.02,
          0.02,
          0.02,
          0.02,
          0.02,
          0.02,
          0.02,
          0.02,
          0.02,
          0.02,
          0.02,
          0.02,
          0.02
        ],
        "old_times": [
          0.02,
          0.02,
          0.02,
          0.02,
          0.02,
          0.02,
          0.02,
          0.02,
          0.02,
          0.02,
          0.02,
          0.02,
          0.02,
          0.02,
          0.02,
          0.02,
          0.02,
          0.02,
          0.02,
          0.02,
          0.02,
          0.02,
          0.02,
          0.02,
          0.02,
          0.02,
          0.02,
          0.02,
          0.02
        ]
      },
      {
        "test_name": "snapshot",
        "is_significant": false,
        "p_value": 1.0,
        "is_pair_significant": false,
        "pair_p_value": 1.0,
        "is_binom_significant": false,
        "binom_p_value": 1.0,
        "is_wilcoxon_significant": false,
        "wilcoxon_p_value": 0.9999999638108507,
        "is_mannwhitney_significant": false,
        "mannwhitney_p_value": 1.0,
        "relative_improvement": 0.0,
        "absolute_improvement_ms": 0.0,
        "old_mean_ms": 10.000000000000002,
        "new_mean_ms": 10.000000000000002,
        "old_std_ms": 1.7654289301252243e-15,
        "new_std_ms": 1.7654289301252243e-15,
        "effect_size_cohens_d": 0.0,
        "old_ci95_ms": [
          10.000000000000002,
          10.000000000000002
        ],
        "new_ci95_ms": [
          10.000000000000002,
          10.000000000000002
        ],
        "old_ci99_ms": [
          10.0,
          10.000000000000004
        ],
        "new_ci99_ms": [
          10.0,
          10.000000000000004
        ],
        "new_times": [
          0.01,
          0.01,
          0.01,
          0.01,
          0.01,
          0.01,
          0.01,
          0.01,
          0.01,
          0.01,
          0.01,
          0.01,
          0.01,
          0.01,
          0.01,
          0.01,
          0.01,
          0.01,
          0.01,
          0.01,
          0.01,
          0.01,
          0.01,
          0.01,
          0.01,
          0.01,
          0.01,
          0.01,
          0.01
        ],
        "old_times": [
          0.01,
          0.01,
          0.01,
          0.01,
          0.01,
          0.01,
          0.01,
          0.01,
          0.01,
          0.01,
          0.01,
          0.01,
          0.01,
          0.01,
          0.01,
          0.01,
          0.01,
          0.01,
          0.01,
          0.01,
          0.01,
          0.01,
          0.01,
          0.01,
          0.01,
          0.01,
          0.01,
          0.01,
          0.01
        ]
      },
      {
        "test_name": "sparse_set",
        "is_significant": false,
        "p_value": 1.0,
        "is_pair_significant": false,
        "pair_p_value": 1.0,
        "is_binom_significant": false,
        "binom_p_value": 1.0,
        "is_wilcoxon_significant": false,
        "wilcoxon_p_value": 0.9999999638108507,
        "is_mannwhitney_significant": false,
        "mannwhitney_p_value": 1.0,
        "relative_improvement": 0.0,
        "absolute_improvement_ms": 0.0,
        "old_mean_ms": 120.00000000000001,
        "new_mean_ms": 120.00000000000001,
        "old_std_ms": 1.4123431441001795e-14,
        "new_std_ms": 1.4123431441001795e-14,
        "effect_size_cohens_d": 0.0,
        "old_ci95_ms": [
          120.00000000000001,
          120.00000000000001
        ],
        "new_ci95_ms": [
          120.00000000000001,
          120.00000000000001
        ],
        "old_ci99_ms": [
          120.0,
          120.00000000000003
        ],
        "new_ci99_ms": [
          120.0,
          120.00000000000003
        ],
        "new_times": [
          0.12,
          0.12,
          0.12,
          0.12,
          0.12,
          0.12,
          0.12,
          0.12,
          0.12,
          0.12,
          0.12,
          0.12,
          0.12,
          0.12,
          0.12,
          0.12,
          0.12,
          0.12,
          0.12,
          0.12,
          0.12,
          0.12,
          0.12,
          0.12,
          0.12,
          0.12,
          0.12,
          0.12,
          0.12
        ],
        "old_times": [
          0.12,
          0.12,
          0.12,
          0.12,
          0.12,
          0.12,
          0.12,
          0.12,
          0.12,
          0.12,
          0.12,
          0.12,
          0.12,
          0.12,
          0.12,
          0.12,
          0.12,
          0.12,
          0.12,
          0.12,
          0.12,
          0.12,
          0.12,
          0.12,
          0.12,
          0.12,
          0.12,
          0.12,
          0.12
        ]
      },
      {
        "test_name": "storage",
        "is_significant": false,
        "p_value": 0.9435866657101581,
        "is_pair_significant": false,
        "pair_p_value": 0.939372407853521,
        "is_binom_significant": false,
        "binom_p_value": 0.9999923817813396,
        "is_wilcoxon_significant": false,
        "wilcoxon_p_value": 0.997454486432671,
        "is_mannwhitney_significant": false,
        "mannwhitney_p_value": 0.5047404400288404,
        "relative_improvement": 0.0,
        "absolute_improvement_ms": 0.0,
        "old_mean_ms": 31.724137931034484,
        "new_mean_ms": 31.724137931034484,
        "old_std_ms": 3.844258722192448,
        "new_std_ms": 3.844258722192448,
        "effect_size_cohens_d": 0.0,
        "old_ci95_ms": [
          30.26186011717537,
          33.186415744893594
        ],
        "new_ci95_ms": [
          30.26186011717537,
          33.186415744893594
        ],
        "old_ci99_ms": [
          29.751552842823312,
          33.69672301924566
        ],
        "new_ci99_ms": [
          29.751552842823312,
          33.69672301924566
        ],
        "new_times": [
          0.03,
          0.03,
          0.03,
          0.03,
          0.04,
          0.03,
          0.03,
          0.03,
          0.03,
          0.03,
          0.03,
          0.03,
          0.04,
          0.03,
          0.03,
          0.03,
          0.03,
          0.03,
          0.03,
          0.03,
          0.03,
          0.03,
          0.04,
          0.03,
          0.03,
          0.03,
          0.04,
          0.03,
          0.04
        ],
        "old_times": [
          0.03,
          0.03,
          0.03,
          0.03,
          0.03,
          0.03,
          0.04,
          0.04,
          0.03,
          0.03,
          0.03,
          0.03,
          0.04,
          0.03,
          0.04,
          0.03,
          0.03,
          0.03,
          0.03,
          0.03,
          0.03,
          0.03,
          0.03,
          0.03,
          0.04,
          0.03,
          0.03,
          0.03,
          0.03
        ]
      },
      {
        "test_name": "storage_entity",
        "is_significant": false,
        "p_value": 1.0,
        "is_pair_significant": false,
        "pair_p_value": 1.0,
        "is_binom_significant": false,
        "binom_p_value": 1.0,
        "is_wilcoxon_significant": false,
        "wilcoxon_p_value": 0.9999999638108507,
        "is_mannwhitney_significant": false,
        "mannwhitney_p_value": 1.0,
        "relative_improvement": 0.0,
        "absolute_improvement_ms": 0.0,
        "old_mean_ms": 10.000000000000002,
        "new_mean_ms": 10.000000000000002,
        "old_std_ms": 1.7654289301252243e-15,
        "new_std_ms": 1.7654289301252243e-15,
        "effect_size_cohens_d": 0.0,
        "old_ci95_ms": [
          10.000000000000002,
          10.000000000000002
        ],
        "new_ci95_ms": [
          10.000000000000002,
          10.000000000000002
        ],
        "old_ci99_ms": [
          10.0,
          10.000000000000004
        ],
        "new_ci99_ms": [
          10.0,
          10.000000000000004
        ],
        "new_times": [
          0.01,
          0.01,
          0.01,
          0.01,
          0.01,
          0.01,
          0.01,
          0.01,
          0.01,
          0.01,
          0.01,
          0.01,
          0.01,
          0.01,
          0.01,
          0.01,
          0.01,
          0.01,
          0.01,
          0.01,
          0.01,
          0.01,
          0.01,
          0.01,
          0.01,
          0.01,
          0.01,
          0.01,
          0.01
        ],
        "old_times": [
          0.01,
          0.01,
          0.01,
          0.01,
          0.01,
          0.01,
          0.01,
          0.01,
          0.01,
          0.01,
          0.01,
          0.01,
          0.01,
          0.01,
          0.01,
          0.01,
          0.01,
          0.01,
          0.01,
          0.01,
          0.01,
          0.01,
          0.01,
          0.01,
          0.01,
          0.01,
          0.01,
          0.01,
          0.01
        ]
      },
      {
        "test_name": "storage_no_instance",
        "is_significant": false,
        "p_value": 1.0,
        "is_pair_significant": false,
        "pair_p_value": 1.0,
        "is_binom_significant": false,
        "binom_p_value": 1.0,
        "is_wilcoxon_significant": false,
        "wilcoxon_p_value": 0.9999999638108507,
        "is_mannwhitney_significant": false,
        "mannwhitney_p_value": 1.0,
        "relative_improvement": 0.0,
        "absolute_improvement_ms": 0.0,
        "old_mean_ms": 40.00000000000001,
        "new_mean_ms": 40.00000000000001,
        "old_std_ms": 7.061715720500897e-15,
        "new_std_ms": 7.061715720500897e-15,
        "effect_size_cohens_d": 0.0,
        "old_ci95_ms": [
          40.00000000000001,
          40.00000000000001
        ],
        "new_ci95_ms": [
          40.00000000000001,
          40.00000000000001
        ],
        "old_ci99_ms": [
          40.0,
          40.000000000000014
        ],
        "new_ci99_ms": [
          40.0,
          40.000000000000014
        ],
        "new_times": [
          0.04,
          0.04,
          0.04,
          0.04,
          0.04,
          0.04,
          0.04,
          0.04,
          0.04,
          0.04,
          0.04,
          0.04,
          0.04,
          0.04,
          0.04,
          0.04,
          0.04,
          0.04,
          0.04,
          0.04,
          0.04,
          0.04,
          0.04,
          0.04,
          0.04,
          0.04,
          0.04,
          0.04,
          0.04
        ],
        "old_times": [
          0.04,
          0.04,
          0.04,
          0.04,
          0.04,
          0.04,
          0.04,
          0.04,
          0.04,
          0.04,
          0.04,
          0.04,
          0.04,
          0.04,
          0.04,
          0.04,
          0.04,
          0.04,
          0.04,
          0.04,
          0.04,
          0.04,
          0.04,
          0.04,
          0.04,
          0.04,
          0.04,
          0.04,
          0.04
        ]
      },
      {
        "test_name": "flow",
        "is_significant": false,
        "p_value": 1.0,
        "is_pair_significant": false,
        "pair_p_value": 1.0,
        "is_binom_significant": false,
        "binom_p_value": 1.0,
        "is_wilcoxon_significant": false,
        "wilcoxon_p_value": 0.9999999638108507,
        "is_mannwhitney_significant": false,
        "mannwhitney_p_value": 1.0,
        "relative_improvement": 0.0,
        "absolute_improvement_ms": 0.0,
        "old_mean_ms": 10.000000000000002,
        "new_mean_ms": 10.000000000000002,
        "old_std_ms": 1.7654289301252243e-15,
        "new_std_ms": 1.7654289301252243e-15,
        "effect_size_cohens_d": 0.0,
        "old_ci95_ms": [
          10.000000000000002,
          10.000000000000002
        ],
        "new_ci95_ms": [
          10.000000000000002,
          10.000000000000002
        ],
        "old_ci99_ms": [
          10.0,
          10.000000000000004
        ],
        "new_ci99_ms": [
          10.0,
          10.000000000000004
        ],
        "new_times": [
          0.01,
          0.01,
          0.01,
          0.01,
          0.01,
          0.01,
          0.01,
          0.01,
          0.01,
          0.01,
          0.01,
          0.01,
          0.01,
          0.01,
          0.01,
          0.01,
          0.01,
          0.01,
          0.01,
          0.01,
          0.01,
          0.01,
          0.01,
          0.01,
          0.01,
          0.01,
          0.01,
          0.01,
          0.01
        ],
        "old_times": [
          0.01,
          0.01,
          0.01,
          0.01,
          0.01,
          0.01,
          0.01,
          0.01,
          0.01,
          0.01,
          0.01,
          0.01,
          0.01,
          0.01,
          0.01,
          0.01,
          0.01,
          0.01,
          0.01,
          0.01,
          0.01,
          0.01,
          0.01,
          0.01,
          0.01,
          0.01,
          0.01,
          0.01,
          0.01
        ]
      },
      {
        "test_name": "meta_any",
        "is_significant": false,
        "p_value": 1.0,
        "is_pair_significant": false,
        "pair_p_value": 1.0,
        "is_binom_significant": false,
        "binom_p_value": 1.0,
        "is_wilcoxon_significant": false,
        "wilcoxon_p_value": 0.9999999638108507,
        "is_mannwhitney_significant": false,
        "mannwhitney_p_value": 1.0,
        "relative_improvement": 0.0,
        "absolute_improvement_ms": 0.0,
        "old_mean_ms": 10.000000000000002,
        "new_mean_ms": 10.000000000000002,
        "old_std_ms": 1.7654289301252243e-15,
        "new_std_ms": 1.7654289301252243e-15,
        "effect_size_cohens_d": 0.0,
        "old_ci95_ms": [
          10.000000000000002,
          10.000000000000002
        ],
        "new_ci95_ms": [
          10.000000000000002,
          10.000000000000002
        ],
        "old_ci99_ms": [
          10.0,
          10.000000000000004
        ],
        "new_ci99_ms": [
          10.0,
          10.000000000000004
        ],
        "new_times": [
          0.01,
          0.01,
          0.01,
          0.01,
          0.01,
          0.01,
          0.01,
          0.01,
          0.01,
          0.01,
          0.01,
          0.01,
          0.01,
          0.01,
          0.01,
          0.01,
          0.01,
          0.01,
          0.01,
          0.01,
          0.01,
          0.01,
          0.01,
          0.01,
          0.01,
          0.01,
          0.01,
          0.01,
          0.01
        ],
        "old_times": [
          0.01,
          0.01,
          0.01,
          0.01,
          0.01,
          0.01,
          0.01,
          0.01,
          0.01,
          0.01,
          0.01,
          0.01,
          0.01,
          0.01,
          0.01,
          0.01,
          0.01,
          0.01,
          0.01,
          0.01,
          0.01,
          0.01,
          0.01,
          0.01,
          0.01,
          0.01,
          0.01,
          0.01,
          0.01
        ]
      },
      {
        "test_name": "meta_container",
        "is_significant": false,
        "p_value": 1.0,
        "is_pair_significant": false,
        "pair_p_value": 1.0,
        "is_binom_significant": false,
        "binom_p_value": 1.0,
        "is_wilcoxon_significant": false,
        "wilcoxon_p_value": 0.9999999638108507,
        "is_mannwhitney_significant": false,
        "mannwhitney_p_value": 1.0,
        "relative_improvement": 0.0,
        "absolute_improvement_ms": 0.0,
        "old_mean_ms": 20.000000000000004,
        "new_mean_ms": 20.000000000000004,
        "old_std_ms": 3.5308578602504487e-15,
        "new_std_ms": 3.5308578602504487e-15,
        "effect_size_cohens_d": 0.0,
        "old_ci95_ms": [
          20.000000000000004,
          20.000000000000004
        ],
        "new_ci95_ms": [
          20.000000000000004,
          20.000000000000004
        ],
        "old_ci99_ms": [
          20.0,
          20.000000000000007
        ],
        "new_ci99_ms": [
          20.0,
          20.000000000000007
        ],
        "new_times": [
          0.02,
          0.02,
          0.02,
          0.02,
          0.02,
          0.02,
          0.02,
          0.02,
          0.02,
          0.02,
          0.02,
          0.02,
          0.02,
          0.02,
          0.02,
          0.02,
          0.02,
          0.02,
          0.02,
          0.02,
          0.02,
          0.02,
          0.02,
          0.02,
          0.02,
          0.02,
          0.02,
          0.02,
          0.02
        ],
        "old_times": [
          0.02,
          0.02,
          0.02,
          0.02,
          0.02,
          0.02,
          0.02,
          0.02,
          0.02,
          0.02,
          0.02,
          0.02,
          0.02,
          0.02,
          0.02,
          0.02,
          0.02,
          0.02,
          0.02,
          0.02,
          0.02,
          0.02,
          0.02,
          0.02,
          0.02,
          0.02,
          0.02,
          0.02,
          0.02
        ]
      },
      {
        "test_name": "meta_custom",
        "is_significant": false,
        "p_value": 1.0,
        "is_pair_significant": false,
        "pair_p_value": 1.0,
        "is_binom_significant": false,
        "binom_p_value": 1.0,
        "is_wilcoxon_significant": false,
        "wilcoxon_p_value": 0.9999999638108507,
        "is_mannwhitney_significant": false,
        "mannwhitney_p_value": 1.0,
        "relative_improvement": 0.0,
        "absolute_improvement_ms": 0.0,
        "old_mean_ms": 10.000000000000002,
        "new_mean_ms": 10.000000000000002,
        "old_std_ms": 1.7654289301252243e-15,
        "new_std_ms": 1.7654289301252243e-15,
        "effect_size_cohens_d": 0.0,
        "old_ci95_ms": [
          10.000000000000002,
          10.000000000000002
        ],
        "new_ci95_ms": [
          10.000000000000002,
          10.000000000000002
        ],
        "old_ci99_ms": [
          10.0,
          10.000000000000004
        ],
        "new_ci99_ms": [
          10.0,
          10.000000000000004
        ],
        "new_times": [
          0.01,
          0.01,
          0.01,
          0.01,
          0.01,
          0.01,
          0.01,
          0.01,
          0.01,
          0.01,
          0.01,
          0.01,
          0.01,
          0.01,
          0.01,
          0.01,
          0.01,
          0.01,
          0.01,
          0.01,
          0.01,
          0.01,
          0.01,
          0.01,
          0.01,
          0.01,
          0.01,
          0.01,
          0.01
        ],
        "old_times": [
          0.01,
          0.01,
          0.01,
          0.01,
          0.01,
          0.01,
          0.01,
          0.01,
          0.01,
          0.01,
          0.01,
          0.01,
          0.01,
          0.01,
          0.01,
          0.01,
          0.01,
          0.01,
          0.01,
          0.01,
          0.01,
          0.01,
          0.01,
          0.01,
          0.01,
          0.01,
          0.01,
          0.01,
          0.01
        ]
      },
      {
        "test_name": "meta_data",
        "is_significant": false,
        "p_value": 1.0,
        "is_pair_significant": false,
        "pair_p_value": 1.0,
        "is_binom_significant": false,
        "binom_p_value": 1.0,
        "is_wilcoxon_significant": false,
        "wilcoxon_p_value": 0.9999999638108507,
        "is_mannwhitney_significant": false,
        "mannwhitney_p_value": 1.0,
        "relative_improvement": 0.0,
        "absolute_improvement_ms": 0.0,
        "old_mean_ms": 10.000000000000002,
        "new_mean_ms": 10.000000000000002,
        "old_std_ms": 1.7654289301252243e-15,
        "new_std_ms": 1.7654289301252243e-15,
        "effect_size_cohens_d": 0.0,
        "old_ci95_ms": [
          10.000000000000002,
          10.000000000000002
        ],
        "new_ci95_ms": [
          10.000000000000002,
          10.000000000000002
        ],
        "old_ci99_ms": [
          10.0,
          10.000000000000004
        ],
        "new_ci99_ms": [
          10.0,
          10.000000000000004
        ],
        "new_times": [
          0.01,
          0.01,
          0.01,
          0.01,
          0.01,
          0.01,
          0.01,
          0.01,
          0.01,
          0.01,
          0.01,
          0.01,
          0.01,
          0.01,
          0.01,
          0.01,
          0.01,
          0.01,
          0.01,
          0.01,
          0.01,
          0.01,
          0.01,
          0.01,
          0.01,
          0.01,
          0.01,
          0.01,
          0.01
        ],
        "old_times": [
          0.01,
          0.01,
          0.01,
          0.01,
          0.01,
          0.01,
          0.01,
          0.01,
          0.01,
          0.01,
          0.01,
          0.01,
          0.01,
          0.01,
          0.01,
          0.01,
          0.01,
          0.01,
          0.01,
          0.01,
          0.01,
          0.01,
          0.01,
          0.01,
          0.01,
          0.01,
          0.01,
          0.01,
          0.01
        ]
      },
      {
        "test_name": "meta_func",
        "is_significant": false,
        "p_value": 1.0,
        "is_pair_significant": false,
        "pair_p_value": 1.0,
        "is_binom_significant": false,
        "binom_p_value": 1.0,
        "is_wilcoxon_significant": false,
        "wilcoxon_p_value": 0.9999999638108507,
        "is_mannwhitney_significant": false,
        "mannwhitney_p_value": 1.0,
        "relative_improvement": 0.0,
        "absolute_improvement_ms": 0.0,
        "old_mean_ms": 10.000000000000002,
        "new_mean_ms": 10.000000000000002,
        "old_std_ms": 1.7654289301252243e-15,
        "new_std_ms": 1.7654289301252243e-15,
        "effect_size_cohens_d": 0.0,
        "old_ci95_ms": [
          10.000000000000002,
          10.000000000000002
        ],
        "new_ci95_ms": [
          10.000000000000002,
          10.000000000000002
        ],
        "old_ci99_ms": [
          10.0,
          10.000000000000004
        ],
        "new_ci99_ms": [
          10.0,
          10.000000000000004
        ],
        "new_times": [
          0.01,
          0.01,
          0.01,
          0.01,
          0.01,
          0.01,
          0.01,
          0.01,
          0.01,
          0.01,
          0.01,
          0.01,
          0.01,
          0.01,
          0.01,
          0.01,
          0.01,
          0.01,
          0.01,
          0.01,
          0.01,
          0.01,
          0.01,
          0.01,
          0.01,
          0.01,
          0.01,
          0.01,
          0.01
        ],
        "old_times": [
          0.01,
          0.01,
          0.01,
          0.01,
          0.01,
          0.01,
          0.01,
          0.01,
          0.01,
          0.01,
          0.01,
          0.01,
          0.01,
          0.01,
          0.01,
          0.01,
          0.01,
          0.01,
          0.01,
          0.01,
          0.01,
          0.01,
          0.01,
          0.01,
          0.01,
          0.01,
          0.01,
          0.01,
          0.01
        ]
      },
      {
        "test_name": "meta_pointer",
        "is_significant": false,
        "p_value": 1.0,
        "is_pair_significant": false,
        "pair_p_value": 1.0,
        "is_binom_significant": false,
        "binom_p_value": 1.0,
        "is_wilcoxon_significant": false,
        "wilcoxon_p_value": 0.9999999638108507,
        "is_mannwhitney_significant": false,
        "mannwhitney_p_value": 1.0,
        "relative_improvement": 0.0,
        "absolute_improvement_ms": 0.0,
        "old_mean_ms": 10.000000000000002,
        "new_mean_ms": 10.000000000000002,
        "old_std_ms": 1.7654289301252243e-15,
        "new_std_ms": 1.7654289301252243e-15,
        "effect_size_cohens_d": 0.0,
        "old_ci95_ms": [
          10.000000000000002,
          10.000000000000002
        ],
        "new_ci95_ms": [
          10.000000000000002,
          10.000000000000002
        ],
        "old_ci99_ms": [
          10.0,
          10.000000000000004
        ],
        "new_ci99_ms": [
          10.0,
          10.000000000000004
        ],
        "new_times": [
          0.01,
          0.01,
          0.01,
          0.01,
          0.01,
          0.01,
          0.01,
          0.01,
          0.01,
          0.01,
          0.01,
          0.01,
          0.01,
          0.01,
          0.01,
          0.01,
          0.01,
          0.01,
          0.01,
          0.01,
          0.01,
          0.01,
          0.01,
          0.01,
          0.01,
          0.01,
          0.01,
          0.01,
          0.01
        ],
        "old_times": [
          0.01,
          0.01,
          0.01,
          0.01,
          0.01,
          0.01,
          0.01,
          0.01,
          0.01,
          0.01,
          0.01,
          0.01,
          0.01,
          0.01,
          0.01,
          0.01,
          0.01,
          0.01,
          0.01,
          0.01,
          0.01,
          0.01,
          0.01,
          0.01,
          0.01,
          0.01,
          0.01,
          0.01,
          0.01
        ]
      },
      {
        "test_name": "meta_type",
        "is_significant": false,
        "p_value": 1.0,
        "is_pair_significant": false,
        "pair_p_value": 1.0,
        "is_binom_significant": false,
        "binom_p_value": 1.0,
        "is_wilcoxon_significant": false,
        "wilcoxon_p_value": 0.9999999638108507,
        "is_mannwhitney_significant": false,
        "mannwhitney_p_value": 1.0,
        "relative_improvement": 0.0,
        "absolute_improvement_ms": 0.0,
        "old_mean_ms": 10.000000000000002,
        "new_mean_ms": 10.000000000000002,
        "old_std_ms": 1.7654289301252243e-15,
        "new_std_ms": 1.7654289301252243e-15,
        "effect_size_cohens_d": 0.0,
        "old_ci95_ms": [
          10.000000000000002,
          10.000000000000002
        ],
        "new_ci95_ms": [
          10.000000000000002,
          10.000000000000002
        ],
        "old_ci99_ms": [
          10.0,
          10.000000000000004
        ],
        "new_ci99_ms": [
          10.0,
          10.000000000000004
        ],
        "new_times": [
          0.01,
          0.01,
          0.01,
          0.01,
          0.01,
          0.01,
          0.01,
          0.01,
          0.01,
          0.01,
          0.01,
          0.01,
          0.01,
          0.01,
          0.01,
          0.01,
          0.01,
          0.01,
          0.01,
          0.01,
          0.01,
          0.01,
          0.01,
          0.01,
          0.01,
          0.01,
          0.01,
          0.01,
          0.01
        ],
        "old_times": [
          0.01,
          0.01,
          0.01,
          0.01,
          0.01,
          0.01,
          0.01,
          0.01,
          0.01,
          0.01,
          0.01,
          0.01,
          0.01,
          0.01,
          0.01,
          0.01,
          0.01,
          0.01,
          0.01,
          0.01,
          0.01,
          0.01,
          0.01,
          0.01,
          0.01,
          0.01,
          0.01,
          0.01,
          0.01
        ]
      },
      {
        "test_name": "meta_utility",
        "is_significant": false,
        "p_value": 1.0,
        "is_pair_significant": false,
        "pair_p_value": 1.0,
        "is_binom_significant": false,
        "binom_p_value": 1.0,
        "is_wilcoxon_significant": false,
        "wilcoxon_p_value": 0.9999999638108507,
        "is_mannwhitney_significant": false,
        "mannwhitney_p_value": 1.0,
        "relative_improvement": 0.0,
        "absolute_improvement_ms": 0.0,
        "old_mean_ms": 10.000000000000002,
        "new_mean_ms": 10.000000000000002,
        "old_std_ms": 1.7654289301252243e-15,
        "new_std_ms": 1.7654289301252243e-15,
        "effect_size_cohens_d": 0.0,
        "old_ci95_ms": [
          10.000000000000002,
          10.000000000000002
        ],
        "new_ci95_ms": [
          10.000000000000002,
          10.000000000000002
        ],
        "old_ci99_ms": [
          10.0,
          10.000000000000004
        ],
        "new_ci99_ms": [
          10.0,
          10.000000000000004
        ],
        "new_times": [
          0.01,
          0.01,
          0.01,
          0.01,
          0.01,
          0.01,
          0.01,
          0.01,
          0.01,
          0.01,
          0.01,
          0.01,
          0.01,
          0.01,
          0.01,
          0.01,
          0.01,
          0.01,
          0.01,
          0.01,
          0.01,
          0.01,
          0.01,
          0.01,
          0.01,
          0.01,
          0.01,
          0.01,
          0.01
        ],
        "old_times": [
          0.01,
          0.01,
          0.01,
          0.01,
          0.01,
          0.01,
          0.01,
          0.01,
          0.01,
          0.01,
          0.01,
          0.01,
          0.01,
          0.01,
          0.01,
          0.01,
          0.01,
          0.01,
          0.01,
          0.01,
          0.01,
          0.01,
          0.01,
          0.01,
          0.01,
          0.01,
          0.01,
          0.01,
          0.01
        ]
      },
      {
        "test_name": "poly",
        "is_significant": false,
        "p_value": 1.0,
        "is_pair_significant": false,
        "pair_p_value": 1.0,
        "is_binom_significant": false,
        "binom_p_value": 1.0,
        "is_wilcoxon_significant": false,
        "wilcoxon_p_value": 0.9999999638108507,
        "is_mannwhitney_significant": false,
        "mannwhitney_p_value": 1.0,
        "relative_improvement": 0.0,
        "absolute_improvement_ms": 0.0,
        "old_mean_ms": 10.000000000000002,
        "new_mean_ms": 10.000000000000002,
        "old_std_ms": 1.7654289301252243e-15,
        "new_std_ms": 1.7654289301252243e-15,
        "effect_size_cohens_d": 0.0,
        "old_ci95_ms": [
          10.000000000000002,
          10.000000000000002
        ],
        "new_ci95_ms": [
          10.000000000000002,
          10.000000000000002
        ],
        "old_ci99_ms": [
          10.0,
          10.000000000000004
        ],
        "new_ci99_ms": [
          10.0,
          10.000000000000004
        ],
        "new_times": [
          0.01,
          0.01,
          0.01,
          0.01,
          0.01,
          0.01,
          0.01,
          0.01,
          0.01,
          0.01,
          0.01,
          0.01,
          0.01,
          0.01,
          0.01,
          0.01,
          0.01,
          0.01,
          0.01,
          0.01,
          0.01,
          0.01,
          0.01,
          0.01,
          0.01,
          0.01,
          0.01,
          0.01,
          0.01
        ],
        "old_times": [
          0.01,
          0.01,
          0.01,
          0.01,
          0.01,
          0.01,
          0.01,
          0.01,
          0.01,
          0.01,
          0.01,
          0.01,
          0.01,
          0.01,
          0.01,
          0.01,
          0.01,
          0.01,
          0.01,
          0.01,
          0.01,
          0.01,
          0.01,
          0.01,
          0.01,
          0.01,
          0.01,
          0.01,
          0.01
        ]
      },
      {
        "test_name": "delegate",
        "is_significant": false,
        "p_value": 1.0,
        "is_pair_significant": false,
        "pair_p_value": 1.0,
        "is_binom_significant": false,
        "binom_p_value": 1.0,
        "is_wilcoxon_significant": false,
        "wilcoxon_p_value": 0.9999999638108507,
        "is_mannwhitney_significant": false,
        "mannwhitney_p_value": 1.0,
        "relative_improvement": 0.0,
        "absolute_improvement_ms": 0.0,
        "old_mean_ms": 10.000000000000002,
        "new_mean_ms": 10.000000000000002,
        "old_std_ms": 1.7654289301252243e-15,
        "new_std_ms": 1.7654289301252243e-15,
        "effect_size_cohens_d": 0.0,
        "old_ci95_ms": [
          10.000000000000002,
          10.000000000000002
        ],
        "new_ci95_ms": [
          10.000000000000002,
          10.000000000000002
        ],
        "old_ci99_ms": [
          10.0,
          10.000000000000004
        ],
        "new_ci99_ms": [
          10.0,
          10.000000000000004
        ],
        "new_times": [
          0.01,
          0.01,
          0.01,
          0.01,
          0.01,
          0.01,
          0.01,
          0.01,
          0.01,
          0.01,
          0.01,
          0.01,
          0.01,
          0.01,
          0.01,
          0.01,
          0.01,
          0.01,
          0.01,
          0.01,
          0.01,
          0.01,
          0.01,
          0.01,
          0.01,
          0.01,
          0.01,
          0.01,
          0.01
        ],
        "old_times": [
          0.01,
          0.01,
          0.01,
          0.01,
          0.01,
          0.01,
          0.01,
          0.01,
          0.01,
          0.01,
          0.01,
          0.01,
          0.01,
          0.01,
          0.01,
          0.01,
          0.01,
          0.01,
          0.01,
          0.01,
          0.01,
          0.01,
          0.01,
          0.01,
          0.01,
          0.01,
          0.01,
          0.01,
          0.01
        ]
      },
      {
        "test_name": "sigh",
        "is_significant": false,
        "p_value": 1.0,
        "is_pair_significant": false,
        "pair_p_value": 1.0,
        "is_binom_significant": false,
        "binom_p_value": 1.0,
        "is_wilcoxon_significant": false,
        "wilcoxon_p_value": 0.9999999638108507,
        "is_mannwhitney_significant": false,
        "mannwhitney_p_value": 1.0,
        "relative_improvement": 0.0,
        "absolute_improvement_ms": 0.0,
        "old_mean_ms": 10.000000000000002,
        "new_mean_ms": 10.000000000000002,
        "old_std_ms": 1.7654289301252243e-15,
        "new_std_ms": 1.7654289301252243e-15,
        "effect_size_cohens_d": 0.0,
        "old_ci95_ms": [
          10.000000000000002,
          10.000000000000002
        ],
        "new_ci95_ms": [
          10.000000000000002,
          10.000000000000002
        ],
        "old_ci99_ms": [
          10.0,
          10.000000000000004
        ],
        "new_ci99_ms": [
          10.0,
          10.000000000000004
        ],
        "new_times": [
          0.01,
          0.01,
          0.01,
          0.01,
          0.01,
          0.01,
          0.01,
          0.01,
          0.01,
          0.01,
          0.01,
          0.01,
          0.01,
          0.01,
          0.01,
          0.01,
          0.01,
          0.01,
          0.01,
          0.01,
          0.01,
          0.01,
          0.01,
          0.01,
          0.01,
          0.01,
          0.01,
          0.01,
          0.01
        ],
        "old_times": [
          0.01,
          0.01,
          0.01,
          0.01,
          0.01,
          0.01,
          0.01,
          0.01,
          0.01,
          0.01,
          0.01,
          0.01,
          0.01,
          0.01,
          0.01,
          0.01,
          0.01,
          0.01,
          0.01,
          0.01,
          0.01,
          0.01,
          0.01,
          0.01,
          0.01,
          0.01,
          0.01,
          0.01,
          0.01
        ]
      }
    ]
  },
  "logs": {
    "full_log_path": "/logs/full.log",
    "config_log_path": "/logs/config.log",
    "build_log_path": "/logs/build.log",
    "test_log_path": "/logs/test.log",
    "build_success": true,
    "test_success": true
  },
  "raw_timing_data": {
    "warmup_runs": 1,
    "measurement_runs": 30,
    "min_exec_time_improvement": 0.05,
    "min_p_value": 0.05
  }
}