{
  "metadata": {
    "collection_date": "2026-01-11T17:54:38.728672",
    "repository": "https://github.com/xtensor-stack/xsimd",
    "repository_name": "xtensor-stack/xsimd"
  },
  "commit_info": {
    "old_sha": "ce58d62666c315140eb54042498d93114edbaa68",
    "new_sha": "609ae41b59dd93643bc3653a07732df84d1075a9",
    "commit_message": [
      "Use fma and fms instruction when available to speedup complex multiply\n\nThis leverage the specific layout of xsimd batch of complex."
    ],
    "commit_date": "2024-02-25T16:29:44+00:00",
    "patch": [
      "--- include/xsimd/types/xsimd_batch.hpp\n@@ -1347,8 +1347,8 @@ namespace xsimd\n     template <class T, class A>\n     inline batch<std::complex<T>, A>& batch<std::complex<T>, A>::operator*=(batch const& other) noexcept\n     {\n-        real_batch new_real = real() * other.real() - imag() * other.imag();\n-        real_batch new_imag = real() * other.imag() + imag() * other.real();\n+        real_batch new_real = fms(real(), other.real(), imag() * other.imag());\n+        real_batch new_imag = fma(real(), other.imag(), imag() * other.real());\n         m_real = new_real;\n         m_imag = new_imag;\n         return *this;"
    ],
    "files_changed": [
      {
        "filename": "include/xsimd/types/xsimd_batch.hpp",
        "status": "modified",
        "additions": 2,
        "deletions": 2,
        "changes": 4,
        "patch": "@@ -1347,8 +1347,8 @@ namespace xsimd\n     template <class T, class A>\n     inline batch<std::complex<T>, A>& batch<std::complex<T>, A>::operator*=(batch const& other) noexcept\n     {\n-        real_batch new_real = real() * other.real() - imag() * other.imag();\n-        real_batch new_imag = real() * other.imag() + imag() * other.real();\n+        real_batch new_real = fms(real(), other.real(), imag() * other.imag());\n+        real_batch new_imag = fma(real(), other.imag(), imag() * other.real());\n         m_real = new_real;\n         m_imag = new_imag;\n         return *this;"
      }
    ],
    "lines_added": 2,
    "lines_removed": 2
  },
  "issues": [],
  "pull_requests": [],
  "build_info": {
    "old_build_script": "#!/bin/bash\n#!/bin/bash\ncmake -S /test_workspace/workspace/old -B /test_workspace/workspace/old/build -DCMAKE_BUILD_TYPE=Debug -DCMAKE_EXPORT_COMPILE_COMMANDS=ON -DBUILD_TESTS=ON",
    "new_build_script": "#!/bin/bash\n#!/bin/bash\ncmake -S /test_workspace/workspace/old -B /test_workspace/workspace/old/build -DCMAKE_BUILD_TYPE=Debug -DCMAKE_EXPORT_COMPILE_COMMANDS=ON -DBUILD_TESTS=ON",
    "old_test_script": "#!/bin/bash\ncmake --build /test_workspace/workspace/old/build -- -j 1",
    "new_test_script": "#!/bin/bash\ncmake --build /test_workspace/workspace/old/build -- -j 1",
    "build_system": "cmake"
  },
  "performance_analysis": {
    "is_significant": false,
    "p_value": 1.0,
    "is_pair_significant": false,
    "pair_p_value": 1.0,
    "is_binom_significant": false,
    "binom_p_value": 1.0,
    "is_wilcoxon_significant": false,
    "wilcoxon_p_value": 0.9999991338918834,
    "is_mannwhitney_significant": false,
    "mannwhitney_p_value": 0.003559624235125849,
    "relative_improvement": 0.0013204781816735138,
    "absolute_improvement_ms": 9.400000000001185,
    "old_mean_ms": 7118.633333333251,
    "new_mean_ms": 7109.233333333251,
    "old_std_ms": 15.264299871750532,
    "new_std_ms": 8.989201695725958,
    "effect_size_cohens_d": 0.7504352057698198,
    "old_ci95_ms": [
      7112.933550087824,
      7124.333116578679
    ],
    "new_ci95_ms": [
      7105.87671025551,
      7112.589956410991
    ],
    "old_ci99_ms": [
      7110.951652084348,
      7126.315014582155
    ],
    "new_ci99_ms": [
      7104.709563315048,
      7113.757103351452
    ],
    "new_times_s": [
      7.109999999999917,
      7.107999999999916,
      7.090999999999917,
      7.12299999999992,
      7.1009999999999165,
      7.101999999999917,
      7.111999999999918,
      7.1149999999999185,
      7.101999999999917,
      7.119999999999918,
      7.118999999999916,
      7.101999999999918,
      7.093999999999915,
      7.119999999999917,
      7.130999999999913,
      7.1039999999999175,
      7.097999999999917,
      7.118999999999918,
      7.1119999999999175,
      7.110999999999916,
      7.107999999999916,
      7.109999999999915,
      7.112999999999916,
      7.101999999999913,
      7.119999999999919,
      7.106999999999914,
      7.103999999999917,
      7.108999999999916,
      7.109999999999919,
      7.102999999999916,
      7.106999999999918
    ],
    "old_times_s": [
      7.133999999999918,
      7.1319999999999215,
      7.109999999999919,
      7.117999999999919,
      7.116999999999919,
      7.12099999999992,
      7.118999999999918,
      7.136999999999919,
      7.12199999999992,
      7.116999999999916,
      7.132999999999918,
      7.086999999999916,
      7.113999999999918,
      7.094999999999919,
      7.113999999999916,
      7.150999999999917,
      7.105999999999916,
      7.1119999999999175,
      7.119999999999918,
      7.119999999999919,
      7.106999999999918,
      7.128999999999917,
      7.103999999999916,
      7.140999999999917,
      7.106999999999918,
      7.128999999999917,
      7.136999999999916,
      7.120999999999917,
      7.143999999999919,
      7.096999999999915,
      7.097999999999919
    ]
  },
  "tests": {
    "total_tests": 30,
    "significant_improvements": 0,
    "significant_improvements_tests": [],
    "significant_regressions": 0,
    "significant_regressions_tests": [],
    "significant_pair_improvements": 0,
    "significant_pair_improvements_tests": [],
    "significant_pair_regressions": 0,
    "significant_pair_regressions_tests": [],
    "significant_binom_improvements": 0,
    "significant_binom_improvements_tests": [],
    "significant_binom_regressions": 0,
    "significant_binom_regressions_tests": [],
    "significant_wilcoxon_improvements": 0,
    "significant_wilcoxon_improvements_tests": [],
    "significant_wilcoxon_regressions": 0,
    "significant_wilcoxon_regressions_tests": [],
    "significant_mannwhitney_improvements": 10,
    "significant_mannwhitney_improvements_tests": [
      "[complex exponential]<xsimd::batch<std::complex<float> >>",
      "[complex exponential]<xsimd::batch<std::complex<double> >>",
      "[complex trigonometric]<xsimd::batch<std::complex<double> >>",
      "[exponential]<xsimd::batch<double>>",
      "[hyperbolic]<xsimd::batch<double>>",
      "[poly evaluation]<xsimd::batch<float>>",
      "[poly evaluation]<xsimd::batch<double>>",
      "[select]<xsimd::batch<short unsigned int>>",
      "[select]<xsimd::batch<int>>",
      "[trigonometric]<xsimd::batch<float>>"
    ],
    "significant_mannwhitney_regressions": 6,
    "significant_mannwhitney_regressions_tests": [
      "[complex power]<xsimd::batch<std::complex<float> >>",
      "[error gamma]<xsimd::batch<float>>",
      "[select]<xsimd::batch<unsigned char>>",
      "[select]<xsimd::batch<signed char>>",
      "[select]<xsimd::batch<short int>>",
      "[select]<xsimd::batch<float>>"
    ],
    "tests": [
      {
        "test_name": "[complex exponential]<xsimd::batch<std::complex<float> >>",
        "is_significant": false,
        "p_value": 1.0,
        "is_pair_significant": false,
        "pair_p_value": 1.0,
        "is_binom_significant": false,
        "binom_p_value": 1.0,
        "is_wilcoxon_significant": false,
        "wilcoxon_p_value": 0.9999987668720761,
        "is_mannwhitney_significant": false,
        "mannwhitney_p_value": 0.00016256621704199478,
        "relative_improvement": 0.0043232944969591154,
        "absolute_improvement_ms": 2.034482758620615,
        "old_mean_ms": 470.5862068965517,
        "new_mean_ms": 468.55172413793105,
        "old_std_ms": 1.8995721582073204,
        "new_std_ms": 1.9745923068636324,
        "effect_size_cohens_d": 1.0500852229570845,
        "old_ci95_ms": [
          469.86364829071806,
          471.30876550238526
        ],
        "new_ci95_ms": [
          467.8006293936895,
          469.30281888217263
        ],
        "old_ci99_ms": [
          469.61148901618907,
          471.5609247769143
        ],
        "new_ci99_ms": [
          467.5385115470796,
          469.56493672878247
        ],
        "new_times": [
          0.465,
          0.469,
          0.469,
          0.465,
          0.468,
          0.469,
          0.47,
          0.468,
          0.471,
          0.47,
          0.465,
          0.47,
          0.47,
          0.468,
          0.469,
          0.471,
          0.47,
          0.467,
          0.469,
          0.464,
          0.47,
          0.47,
          0.469,
          0.465,
          0.47,
          0.469,
          0.47,
          0.468,
          0.47
        ],
        "old_times": [
          0.47,
          0.472,
          0.47,
          0.47,
          0.467,
          0.474,
          0.47,
          0.469,
          0.471,
          0.473,
          0.469,
          0.472,
          0.473,
          0.472,
          0.472,
          0.469,
          0.473,
          0.467,
          0.467,
          0.47,
          0.471,
          0.471,
          0.47,
          0.47,
          0.47,
          0.471,
          0.471,
          0.469,
          0.474
        ]
      },
      {
        "test_name": "[complex exponential]<xsimd::batch<std::complex<double> >>",
        "is_significant": false,
        "p_value": 1.0,
        "is_pair_significant": false,
        "pair_p_value": 0.999999999999817,
        "is_binom_significant": false,
        "binom_p_value": 1.0,
        "is_wilcoxon_significant": false,
        "wilcoxon_p_value": 0.999998739031803,
        "is_mannwhitney_significant": false,
        "mannwhitney_p_value": 6.827432822498066e-05,
        "relative_improvement": 0.009899342816737359,
        "absolute_improvement_ms": 4.103448275862121,
        "old_mean_ms": 414.5172413793104,
        "new_mean_ms": 410.41379310344826,
        "old_std_ms": 5.322597980411785,
        "new_std_ms": 3.54075497779891,
        "effect_size_cohens_d": 0.9077737258622158,
        "old_ci95_ms": [
          412.4926333855985,
          416.5418493730223
        ],
        "new_ci95_ms": [
          409.0669619397555,
          411.76062426714105
        ],
        "old_ci99_ms": [
          411.7860835240671,
          417.24839923455363
        ],
        "new_ci99_ms": [
          408.596943360767,
          412.2306428461295
        ],
        "new_times": [
          0.412,
          0.409,
          0.412,
          0.414,
          0.406,
          0.405,
          0.406,
          0.414,
          0.413,
          0.41,
          0.415,
          0.415,
          0.414,
          0.412,
          0.405,
          0.413,
          0.412,
          0.405,
          0.412,
          0.406,
          0.414,
          0.408,
          0.409,
          0.413,
          0.407,
          0.414,
          0.404,
          0.412,
          0.411
        ],
        "old_times": [
          0.418,
          0.416,
          0.418,
          0.407,
          0.417,
          0.418,
          0.417,
          0.416,
          0.42,
          0.416,
          0.417,
          0.404,
          0.417,
          0.416,
          0.416,
          0.406,
          0.405,
          0.405,
          0.405,
          0.416,
          0.416,
          0.417,
          0.415,
          0.418,
          0.42,
          0.419,
          0.42,
          0.407,
          0.419
        ]
      },
      {
        "test_name": "[complex hyperbolic]<xsimd::batch<std::complex<float> >>",
        "is_significant": false,
        "p_value": 1.0,
        "is_pair_significant": false,
        "pair_p_value": 1.0,
        "is_binom_significant": false,
        "binom_p_value": 1.0,
        "is_wilcoxon_significant": false,
        "wilcoxon_p_value": 0.9999987785279242,
        "is_mannwhitney_significant": false,
        "mannwhitney_p_value": 0.31490960715583977,
        "relative_improvement": 0.0007648981294764626,
        "absolute_improvement_ms": 0.3793103448276325,
        "old_mean_ms": 495.8965517241379,
        "new_mean_ms": 495.51724137931024,
        "old_std_ms": 1.8389598687885456,
        "new_std_ms": 2.33942437448636,
        "effect_size_cohens_d": 0.18026991523408678,
        "old_ci95_ms": [
          495.19704880015854,
          496.5960546481172
        ],
        "new_ci95_ms": [
          494.62737193835295,
          496.4071108202676
        ],
        "old_ci99_ms": [
          494.9529355221248,
          496.84016792615097
        ],
        "new_ci99_ms": [
          494.31682434976193,
          496.71765840885854
        ],
        "new_times": [
          0.498,
          0.497,
          0.492,
          0.495,
          0.491,
          0.496,
          0.495,
          0.496,
          0.497,
          0.491,
          0.495,
          0.498,
          0.497,
          0.493,
          0.492,
          0.497,
          0.493,
          0.497,
          0.497,
          0.495,
          0.497,
          0.495,
          0.497,
          0.497,
          0.5,
          0.492,
          0.497,
          0.498,
          0.495
        ],
        "old_times": [
          0.496,
          0.498,
          0.494,
          0.499,
          0.495,
          0.493,
          0.497,
          0.496,
          0.494,
          0.494,
          0.494,
          0.498,
          0.497,
          0.498,
          0.494,
          0.498,
          0.497,
          0.496,
          0.494,
          0.492,
          0.498,
          0.495,
          0.495,
          0.498,
          0.497,
          0.497,
          0.497,
          0.494,
          0.496
        ]
      },
      {
        "test_name": "[complex hyperbolic]<xsimd::batch<std::complex<double> >>",
        "is_significant": false,
        "p_value": 1.0,
        "is_pair_significant": false,
        "pair_p_value": 1.0,
        "is_binom_significant": false,
        "binom_p_value": 1.0,
        "is_wilcoxon_significant": false,
        "wilcoxon_p_value": 0.9999987466758259,
        "is_mannwhitney_significant": false,
        "mannwhitney_p_value": 0.1212213623473406,
        "relative_improvement": 0.0022998418858703484,
        "absolute_improvement_ms": 1.1034482758621178,
        "old_mean_ms": 479.7931034482759,
        "new_mean_ms": 478.6896551724137,
        "old_std_ms": 5.894181818568621,
        "new_std_ms": 4.158497739361643,
        "effect_size_cohens_d": 0.21633229485983613,
        "old_ci95_ms": [
          477.5510765903049,
          482.03513030624686
        ],
        "new_ci95_ms": [
          477.107847229013,
          480.2714631158145
        ],
        "old_ci99_ms": [
          476.7686516611488,
          482.81755523540295
        ],
        "new_ci99_ms": [
          476.5558262023005,
          480.823484142527
        ],
        "new_times": [
          0.483,
          0.477,
          0.475,
          0.476,
          0.472,
          0.485,
          0.473,
          0.48,
          0.478,
          0.48,
          0.474,
          0.479,
          0.485,
          0.479,
          0.482,
          0.476,
          0.48,
          0.476,
          0.484,
          0.485,
          0.472,
          0.479,
          0.479,
          0.482,
          0.48,
          0.479,
          0.485,
          0.471,
          0.476
        ],
        "old_times": [
          0.486,
          0.486,
          0.487,
          0.481,
          0.474,
          0.483,
          0.473,
          0.485,
          0.484,
          0.471,
          0.481,
          0.469,
          0.482,
          0.482,
          0.483,
          0.474,
          0.481,
          0.488,
          0.481,
          0.486,
          0.474,
          0.486,
          0.482,
          0.483,
          0.484,
          0.472,
          0.471,
          0.472,
          0.473
        ]
      },
      {
        "test_name": "[complex power]<xsimd::batch<std::complex<float> >>",
        "is_significant": false,
        "p_value": 1.0,
        "is_pair_significant": false,
        "pair_p_value": 1.0,
        "is_binom_significant": false,
        "binom_p_value": 1.0,
        "is_wilcoxon_significant": false,
        "wilcoxon_p_value": 0.9999990873905196,
        "is_mannwhitney_significant": false,
        "mannwhitney_p_value": 0.9999989533029325,
        "relative_improvement": -0.004646713133797978,
        "absolute_improvement_ms": -1.172413793103455,
        "old_mean_ms": 252.3103448275862,
        "new_mean_ms": 253.48275862068965,
        "old_std_ms": 0.7123125455595861,
        "new_std_ms": 0.7847060257179314,
        "effect_size_cohens_d": -1.5645034040843226,
        "old_ci95_ms": [
          252.03939562588644,
          252.5812940292859
        ],
        "new_ci95_ms": [
          253.18427241184403,
          253.78124482953524
        ],
        "old_ci99_ms": [
          251.94483948388879,
          252.67585017128357
        ],
        "new_ci99_ms": [
          253.0801063756613,
          253.88541086571797
        ],
        "new_times": [
          0.255,
          0.254,
          0.254,
          0.254,
          0.252,
          0.254,
          0.254,
          0.253,
          0.254,
          0.254,
          0.252,
          0.254,
          0.253,
          0.253,
          0.254,
          0.253,
          0.254,
          0.254,
          0.253,
          0.252,
          0.254,
          0.254,
          0.253,
          0.252,
          0.254,
          0.253,
          0.254,
          0.254,
          0.253
        ],
        "old_times": [
          0.253,
          0.252,
          0.253,
          0.251,
          0.251,
          0.252,
          0.253,
          0.252,
          0.253,
          0.252,
          0.252,
          0.252,
          0.254,
          0.252,
          0.252,
          0.252,
          0.253,
          0.253,
          0.252,
          0.253,
          0.252,
          0.252,
          0.252,
          0.253,
          0.253,
          0.253,
          0.251,
          0.252,
          0.252
        ]
      },
      {
        "test_name": "[complex power]<xsimd::batch<std::complex<double> >>",
        "is_significant": false,
        "p_value": 1.0,
        "is_pair_significant": false,
        "pair_p_value": 1.0,
        "is_binom_significant": false,
        "binom_p_value": 1.0,
        "is_wilcoxon_significant": false,
        "wilcoxon_p_value": 0.9999987500608026,
        "is_mannwhitney_significant": false,
        "mannwhitney_p_value": 0.40117333092215446,
        "relative_improvement": -0.0005336179295623271,
        "absolute_improvement_ms": -0.17241379310339866,
        "old_mean_ms": 323.10344827586215,
        "new_mean_ms": 323.2758620689655,
        "old_std_ms": 3.3630856110997573,
        "new_std_ms": 2.2974605814143407,
        "effect_size_cohens_d": -0.05986613504632754,
        "old_ci95_ms": [
          321.82419892491953,
          324.3826976268047
        ],
        "new_ci95_ms": [
          322.40195480122003,
          324.149769336711
        ],
        "old_ci99_ms": [
          321.37776511917554,
          324.8291314325487
        ],
        "new_ci99_ms": [
          322.09697770889665,
          324.4547464290344
        ],
        "new_times": [
          0.321,
          0.321,
          0.326,
          0.321,
          0.327,
          0.321,
          0.322,
          0.322,
          0.32,
          0.323,
          0.328,
          0.324,
          0.326,
          0.322,
          0.321,
          0.32,
          0.324,
          0.323,
          0.321,
          0.327,
          0.324,
          0.327,
          0.325,
          0.322,
          0.322,
          0.323,
          0.323,
          0.325,
          0.324
        ],
        "old_times": [
          0.317,
          0.317,
          0.319,
          0.327,
          0.326,
          0.325,
          0.328,
          0.324,
          0.319,
          0.318,
          0.324,
          0.326,
          0.323,
          0.326,
          0.324,
          0.319,
          0.324,
          0.324,
          0.324,
          0.327,
          0.319,
          0.325,
          0.325,
          0.319,
          0.32,
          0.327,
          0.326,
          0.325,
          0.323
        ]
      },
      {
        "test_name": "[complex trigonometric]<xsimd::batch<std::complex<float> >>",
        "is_significant": false,
        "p_value": 1.0,
        "is_pair_significant": false,
        "pair_p_value": 1.0,
        "is_binom_significant": false,
        "binom_p_value": 1.0,
        "is_wilcoxon_significant": false,
        "wilcoxon_p_value": 0.9999988080807072,
        "is_mannwhitney_significant": false,
        "mannwhitney_p_value": 0.8191543201709319,
        "relative_improvement": 0.0,
        "absolute_improvement_ms": -1.1102230246251565e-13,
        "old_mean_ms": 564.8620689655172,
        "new_mean_ms": 564.8620689655173,
        "old_std_ms": 1.8268657377172806,
        "new_std_ms": 2.5873888924527706,
        "effect_size_cohens_d": -4.95713834406697e-14,
        "old_ci95_ms": [
          564.1671664029654,
          565.5569715280689
        ],
        "new_ci95_ms": [
          563.8778788662876,
          565.846259064747
        ],
        "old_ci99_ms": [
          563.9246585639795,
          565.7994793670548
        ],
        "new_ci99_ms": [
          563.5344151535634,
          566.1897227774712
        ],
        "new_times": [
          0.561,
          0.565,
          0.565,
          0.56,
          0.568,
          0.566,
          0.567,
          0.568,
          0.566,
          0.565,
          0.563,
          0.56,
          0.566,
          0.565,
          0.56,
          0.567,
          0.566,
          0.567,
          0.561,
          0.567,
          0.567,
          0.566,
          0.567,
          0.565,
          0.567,
          0.566,
          0.565,
          0.565,
          0.56
        ],
        "old_times": [
          0.568,
          0.564,
          0.563,
          0.564,
          0.565,
          0.567,
          0.564,
          0.564,
          0.562,
          0.567,
          0.565,
          0.563,
          0.563,
          0.563,
          0.564,
          0.563,
          0.565,
          0.564,
          0.566,
          0.566,
          0.564,
          0.563,
          0.564,
          0.567,
          0.564,
          0.565,
          0.568,
          0.567,
          0.569
        ]
      },
      {
        "test_name": "[complex trigonometric]<xsimd::batch<std::complex<double> >>",
        "is_significant": false,
        "p_value": 1.0,
        "is_pair_significant": false,
        "pair_p_value": 0.9999999999999996,
        "is_binom_significant": false,
        "binom_p_value": 1.0,
        "is_wilcoxon_significant": false,
        "wilcoxon_p_value": 0.9999987339143248,
        "is_mannwhitney_significant": false,
        "mannwhitney_p_value": 0.0033314575867579785,
        "relative_improvement": 0.006090471180997699,
        "absolute_improvement_ms": 3.7931034482759918,
        "old_mean_ms": 622.793103448276,
        "new_mean_ms": 619.0,
        "old_std_ms": 7.5326873896601425,
        "new_std_ms": 5.586974647721767,
        "effect_size_cohens_d": 0.5719759611726277,
        "old_ci95_ms": [
          619.9278224033118,
          625.6583844932402
        ],
        "new_ci95_ms": [
          616.8748285002791,
          621.1251714997209
        ],
        "old_ci99_ms": [
          618.9278935618494,
          626.6583133347026
        ],
        "new_ci99_ms": [
          616.1331838789392,
          621.8668161210608
        ],
        "new_times": [
          0.61,
          0.627,
          0.614,
          0.624,
          0.622,
          0.619,
          0.627,
          0.622,
          0.621,
          0.61,
          0.611,
          0.621,
          0.625,
          0.61,
          0.627,
          0.621,
          0.627,
          0.622,
          0.621,
          0.615,
          0.621,
          0.612,
          0.619,
          0.614,
          0.618,
          0.621,
          0.62,
          0.61,
          0.62
        ],
        "old_times": [
          0.613,
          0.625,
          0.624,
          0.624,
          0.632,
          0.627,
          0.626,
          0.625,
          0.63,
          0.61,
          0.612,
          0.627,
          0.611,
          0.631,
          0.612,
          0.628,
          0.623,
          0.629,
          0.611,
          0.624,
          0.63,
          0.63,
          0.611,
          0.624,
          0.629,
          0.627,
          0.629,
          0.626,
          0.611
        ]
      },
      {
        "test_name": "[error gamma]<xsimd::batch<float>>",
        "is_significant": false,
        "p_value": 1.0,
        "is_pair_significant": false,
        "pair_p_value": 1.0,
        "is_binom_significant": false,
        "binom_p_value": 1.0,
        "is_wilcoxon_significant": false,
        "wilcoxon_p_value": 0.9999988354438968,
        "is_mannwhitney_significant": false,
        "mannwhitney_p_value": 0.9962005405163604,
        "relative_improvement": -0.0025561684380465666,
        "absolute_improvement_ms": -0.6551724137930925,
        "old_mean_ms": 256.31034482758616,
        "new_mean_ms": 256.9655172413793,
        "old_std_ms": 0.8063785124981446,
        "new_std_ms": 1.3224101001226536,
        "effect_size_cohens_d": -0.5982106481898493,
        "old_ci95_ms": [
          256.0036148456545,
          256.6170748095178
        ],
        "new_ci95_ms": [
          256.46249934118714,
          257.4685351415714
        ],
        "old_ci99_ms": [
          255.89657188872934,
          256.72411776644304
        ],
        "new_ci99_ms": [
          256.28695561675636,
          257.6440788660022
        ],
        "new_times": [
          0.254,
          0.258,
          0.257,
          0.259,
          0.258,
          0.257,
          0.258,
          0.257,
          0.257,
          0.257,
          0.258,
          0.256,
          0.257,
          0.257,
          0.254,
          0.259,
          0.255,
          0.256,
          0.257,
          0.258,
          0.255,
          0.258,
          0.258,
          0.257,
          0.255,
          0.257,
          0.258,
          0.257,
          0.258
        ],
        "old_times": [
          0.255,
          0.256,
          0.257,
          0.256,
          0.256,
          0.256,
          0.255,
          0.257,
          0.256,
          0.257,
          0.256,
          0.256,
          0.258,
          0.256,
          0.257,
          0.256,
          0.256,
          0.256,
          0.256,
          0.256,
          0.256,
          0.257,
          0.257,
          0.257,
          0.257,
          0.255,
          0.257,
          0.258,
          0.255
        ]
      },
      {
        "test_name": "[error gamma]<xsimd::batch<double>>",
        "is_significant": false,
        "p_value": 1.0,
        "is_pair_significant": false,
        "pair_p_value": 1.0,
        "is_binom_significant": false,
        "binom_p_value": 1.0,
        "is_wilcoxon_significant": false,
        "wilcoxon_p_value": 0.9999987568079944,
        "is_mannwhitney_significant": false,
        "mannwhitney_p_value": 0.3975718403323879,
        "relative_improvement": -0.0007966857871255407,
        "absolute_improvement_ms": -0.17241379310345417,
        "old_mean_ms": 216.41379310344828,
        "new_mean_ms": 216.58620689655172,
        "old_std_ms": 2.847520743425141,
        "new_std_ms": 1.8615899767078994,
        "effect_size_cohens_d": -0.0716716328011993,
        "old_ci95_ms": [
          215.33065413999174,
          217.4969320669048
        ],
        "new_ci95_ms": [
          215.87809593988595,
          217.2943178532175
        ],
        "old_ci99_ms": [
          214.95265914687394,
          217.8749270600226
        ],
        "new_ci99_ms": [
          215.63097862140506,
          217.5414351716984
        ],
        "new_times": [
          0.215,
          0.213,
          0.217,
          0.214,
          0.219,
          0.216,
          0.217,
          0.215,
          0.219,
          0.218,
          0.216,
          0.217,
          0.218,
          0.218,
          0.217,
          0.219,
          0.216,
          0.218,
          0.215,
          0.216,
          0.218,
          0.218,
          0.214,
          0.215,
          0.215,
          0.213,
          0.218,
          0.217,
          0.22
        ],
        "old_times": [
          0.21,
          0.219,
          0.216,
          0.219,
          0.22,
          0.218,
          0.217,
          0.217,
          0.217,
          0.219,
          0.212,
          0.211,
          0.218,
          0.22,
          0.217,
          0.216,
          0.214,
          0.212,
          0.217,
          0.213,
          0.217,
          0.217,
          0.217,
          0.212,
          0.219,
          0.216,
          0.219,
          0.217,
          0.22
        ]
      },
      {
        "test_name": "[exponential]<xsimd::batch<float>>",
        "is_significant": false,
        "p_value": 1.0,
        "is_pair_significant": false,
        "pair_p_value": 1.0,
        "is_binom_significant": false,
        "binom_p_value": 1.0,
        "is_wilcoxon_significant": false,
        "wilcoxon_p_value": 0.9999990449500936,
        "is_mannwhitney_significant": false,
        "mannwhitney_p_value": 0.479988493123899,
        "relative_improvement": 0.0,
        "absolute_improvement_ms": 0.0,
        "old_mean_ms": 162.0689655172414,
        "new_mean_ms": 162.0689655172414,
        "old_std_ms": 0.5934785158440644,
        "new_std_ms": 0.9231558637459193,
        "effect_size_cohens_d": 0.0,
        "old_ci95_ms": [
          161.84321836299526,
          162.29471267148753
        ],
        "new_ci95_ms": [
          161.71781580650608,
          162.42011522797674
        ],
        "old_ci99_ms": [
          161.76443687982962,
          162.37349415465317
        ],
        "new_ci99_ms": [
          161.5952712051475,
          162.5426598293353
        ],
        "new_times": [
          0.162,
          0.162,
          0.163,
          0.162,
          0.163,
          0.161,
          0.162,
          0.161,
          0.163,
          0.161,
          0.162,
          0.163,
          0.162,
          0.161,
          0.161,
          0.163,
          0.163,
          0.162,
          0.163,
          0.161,
          0.161,
          0.161,
          0.164,
          0.162,
          0.161,
          0.161,
          0.163,
          0.163,
          0.163
        ],
        "old_times": [
          0.162,
          0.163,
          0.162,
          0.162,
          0.163,
          0.163,
          0.162,
          0.162,
          0.163,
          0.162,
          0.162,
          0.162,
          0.162,
          0.161,
          0.161,
          0.162,
          0.162,
          0.162,
          0.162,
          0.162,
          0.161,
          0.162,
          0.161,
          0.163,
          0.162,
          0.162,
          0.163,
          0.162,
          0.162
        ]
      },
      {
        "test_name": "[exponential]<xsimd::batch<double>>",
        "is_significant": false,
        "p_value": 1.0,
        "is_pair_significant": false,
        "pair_p_value": 1.0,
        "is_binom_significant": false,
        "binom_p_value": 1.0,
        "is_wilcoxon_significant": false,
        "wilcoxon_p_value": 0.999998817798638,
        "is_mannwhitney_significant": false,
        "mannwhitney_p_value": 0.027801983300671268,
        "relative_improvement": 0.0007633587786260396,
        "absolute_improvement_ms": 0.13793103448278554,
        "old_mean_ms": 180.6896551724138,
        "new_mean_ms": 180.55172413793102,
        "old_std_ms": 2.508605877429907,
        "new_std_ms": 0.9481638984506449,
        "effect_size_cohens_d": 0.07273586070307723,
        "old_ci95_ms": [
          179.73543252940962,
          181.643877815418
        ],
        "new_ci95_ms": [
          180.1910618795345,
          180.91238639632758
        ],
        "old_ci99_ms": [
          179.40242689158805,
          181.97688345323957
        ],
        "new_ci99_ms": [
          180.06519757912613,
          181.0382506967359
        ],
        "new_times": [
          0.179,
          0.181,
          0.182,
          0.181,
          0.181,
          0.182,
          0.181,
          0.181,
          0.18,
          0.181,
          0.179,
          0.18,
          0.182,
          0.18,
          0.179,
          0.182,
          0.182,
          0.181,
          0.18,
          0.18,
          0.18,
          0.18,
          0.18,
          0.18,
          0.181,
          0.181,
          0.179,
          0.18,
          0.181
        ],
        "old_times": [
          0.178,
          0.177,
          0.182,
          0.183,
          0.183,
          0.182,
          0.182,
          0.181,
          0.182,
          0.183,
          0.182,
          0.176,
          0.177,
          0.184,
          0.177,
          0.183,
          0.181,
          0.182,
          0.182,
          0.182,
          0.177,
          0.182,
          0.181,
          0.182,
          0.182,
          0.181,
          0.183,
          0.177,
          0.176
        ]
      },
      {
        "test_name": "[hyperbolic]<xsimd::batch<float>>",
        "is_significant": false,
        "p_value": 1.0,
        "is_pair_significant": false,
        "pair_p_value": 1.0,
        "is_binom_significant": false,
        "binom_p_value": 1.0,
        "is_wilcoxon_significant": false,
        "wilcoxon_p_value": 0.9999989076361977,
        "is_mannwhitney_significant": false,
        "mannwhitney_p_value": 0.6367229472577971,
        "relative_improvement": -0.00023640661938542176,
        "absolute_improvement_ms": -0.03448275862066863,
        "old_mean_ms": 145.86206896551724,
        "new_mean_ms": 145.8965517241379,
        "old_std_ms": 0.5808945030255672,
        "new_std_ms": 1.0122403577569525,
        "effect_size_cohens_d": -0.041784715648247976,
        "old_ci95_ms": [
          145.64110851374969,
          146.0830294172848
        ],
        "new_ci95_ms": [
          145.5115160841338,
          146.281587364142
        ],
        "old_ci99_ms": [
          145.56399749913095,
          146.1601404319035
        ],
        "new_ci99_ms": [
          145.37714593496196,
          146.41595751331386
        ],
        "new_times": [
          0.147,
          0.147,
          0.145,
          0.146,
          0.146,
          0.146,
          0.146,
          0.146,
          0.145,
          0.148,
          0.147,
          0.145,
          0.145,
          0.147,
          0.146,
          0.146,
          0.144,
          0.147,
          0.145,
          0.146,
          0.144,
          0.146,
          0.144,
          0.146,
          0.147,
          0.147,
          0.146,
          0.145,
          0.146
        ],
        "old_times": [
          0.146,
          0.146,
          0.146,
          0.146,
          0.146,
          0.146,
          0.147,
          0.145,
          0.147,
          0.145,
          0.145,
          0.146,
          0.146,
          0.146,
          0.146,
          0.146,
          0.146,
          0.145,
          0.145,
          0.146,
          0.146,
          0.146,
          0.146,
          0.145,
          0.145,
          0.146,
          0.146,
          0.147,
          0.146
        ]
      },
      {
        "test_name": "[hyperbolic]<xsimd::batch<double>>",
        "is_significant": false,
        "p_value": 1.0,
        "is_pair_significant": false,
        "pair_p_value": 1.0,
        "is_binom_significant": false,
        "binom_p_value": 1.0,
        "is_wilcoxon_significant": false,
        "wilcoxon_p_value": 0.9999988186054853,
        "is_mannwhitney_significant": false,
        "mannwhitney_p_value": 0.03522472231758676,
        "relative_improvement": 0.001325088339222469,
        "absolute_improvement_ms": 0.2068965517241783,
        "old_mean_ms": 156.1379310344828,
        "new_mean_ms": 155.9310344827586,
        "old_std_ms": 2.1831192940874202,
        "new_std_ms": 1.2798167972341827,
        "effect_size_cohens_d": 0.11562309572597157,
        "old_ci95_ms": [
          155.30751686638249,
          156.9683452025831
        ],
        "new_ci95_ms": [
          155.44421820850627,
          156.41785075701094
        ],
        "old_ci99_ms": [
          155.01771804245843,
          157.25814402650715
        ],
        "new_ci99_ms": [
          155.27432854481214,
          156.58774042070507
        ],
        "new_times": [
          0.157,
          0.158,
          0.154,
          0.154,
          0.156,
          0.157,
          0.154,
          0.156,
          0.155,
          0.155,
          0.155,
          0.158,
          0.156,
          0.159,
          0.157,
          0.157,
          0.156,
          0.154,
          0.154,
          0.156,
          0.156,
          0.156,
          0.156,
          0.156,
          0.155,
          0.156,
          0.156,
          0.157,
          0.156
        ],
        "old_times": [
          0.157,
          0.158,
          0.157,
          0.157,
          0.158,
          0.158,
          0.156,
          0.153,
          0.152,
          0.156,
          0.153,
          0.158,
          0.157,
          0.157,
          0.156,
          0.158,
          0.157,
          0.152,
          0.157,
          0.151,
          0.158,
          0.157,
          0.152,
          0.156,
          0.157,
          0.157,
          0.158,
          0.157,
          0.158
        ]
      },
      {
        "test_name": "[poly evaluation]<xsimd::batch<float>>",
        "is_significant": false,
        "p_value": 1.0,
        "is_pair_significant": false,
        "pair_p_value": 1.0,
        "is_binom_significant": false,
        "binom_p_value": 1.0,
        "is_wilcoxon_significant": false,
        "wilcoxon_p_value": 0.9999995453596235,
        "is_mannwhitney_significant": false,
        "mannwhitney_p_value": 0.006197454876163879,
        "relative_improvement": 0.0045543266102796975,
        "absolute_improvement_ms": 0.24137931034482613,
        "old_mean_ms": 52.99999999999999,
        "new_mean_ms": 52.75862068965517,
        "old_std_ms": 7.061715720500897e-15,
        "new_std_ms": 0.5109635445336242,
        "effect_size_cohens_d": 0.6680748519495483,
        "old_ci95_ms": [
          52.99999999999999,
          52.99999999999999
        ],
        "new_ci95_ms": [
          52.56426055188686,
          52.95298082742347
        ],
        "old_ci99_ms": [
          52.999999999999986,
          53.0
        ],
        "new_ci99_ms": [
          52.49643254327783,
          53.0208088360325
        ],
        "new_times": [
          0.053,
          0.054,
          0.052,
          0.053,
          0.053,
          0.053,
          0.053,
          0.053,
          0.052,
          0.053,
          0.053,
          0.053,
          0.052,
          0.052,
          0.053,
          0.053,
          0.052,
          0.053,
          0.052,
          0.053,
          0.053,
          0.053,
          0.053,
          0.053,
          0.053,
          0.052,
          0.053,
          0.053,
          0.052
        ],
        "old_times": [
          0.053,
          0.053,
          0.053,
          0.053,
          0.053,
          0.053,
          0.053,
          0.053,
          0.053,
          0.053,
          0.053,
          0.053,
          0.053,
          0.053,
          0.053,
          0.053,
          0.053,
          0.053,
          0.053,
          0.053,
          0.053,
          0.053,
          0.053,
          0.053,
          0.053,
          0.053,
          0.053,
          0.053,
          0.053
        ]
      },
      {
        "test_name": "[poly evaluation]<xsimd::batch<double>>",
        "is_significant": false,
        "p_value": 1.0,
        "is_pair_significant": false,
        "pair_p_value": 0.9999999999999437,
        "is_binom_significant": false,
        "binom_p_value": 1.0,
        "is_wilcoxon_significant": false,
        "wilcoxon_p_value": 0.9999991162795316,
        "is_mannwhitney_significant": false,
        "mannwhitney_p_value": 0.037383216096334465,
        "relative_improvement": 0.005594405594405599,
        "absolute_improvement_ms": 0.27586206896551557,
        "old_mean_ms": 49.31034482758621,
        "new_mean_ms": 49.0344827586207,
        "old_std_ms": 0.6037648712076864,
        "new_std_ms": 0.565859562378313,
        "effect_size_cohens_d": 0.4714629895690258,
        "old_ci95_ms": [
          49.08068495301592,
          49.54000470215651
        ],
        "new_ci95_ms": [
          48.81924129241836,
          49.249724224823034
        ],
        "old_ci99_ms": [
          49.00053800452962,
          49.6201516506428
        ],
        "new_ci99_ms": [
          48.74412609549461,
          49.32483942174679
        ],
        "new_times": [
          0.049,
          0.049,
          0.048,
          0.049,
          0.049,
          0.049,
          0.049,
          0.048,
          0.05,
          0.049,
          0.048,
          0.049,
          0.049,
          0.049,
          0.049,
          0.05,
          0.049,
          0.049,
          0.048,
          0.049,
          0.049,
          0.049,
          0.05,
          0.049,
          0.05,
          0.05,
          0.049,
          0.049,
          0.049
        ],
        "old_times": [
          0.049,
          0.049,
          0.049,
          0.049,
          0.049,
          0.049,
          0.049,
          0.05,
          0.05,
          0.05,
          0.05,
          0.049,
          0.049,
          0.05,
          0.05,
          0.049,
          0.05,
          0.049,
          0.05,
          0.05,
          0.048,
          0.048,
          0.049,
          0.049,
          0.05,
          0.049,
          0.049,
          0.05,
          0.049
        ]
      },
      {
        "test_name": "[power]<xsimd::batch<float>>",
        "is_significant": false,
        "p_value": 1.0,
        "is_pair_significant": false,
        "pair_p_value": 1.0,
        "is_binom_significant": false,
        "binom_p_value": 1.0,
        "is_wilcoxon_significant": false,
        "wilcoxon_p_value": 0.9999987643624194,
        "is_mannwhitney_significant": false,
        "mannwhitney_p_value": 0.09706886607703369,
        "relative_improvement": 0.0016086575021936416,
        "absolute_improvement_ms": 0.3793103448275492,
        "old_mean_ms": 235.79310344827584,
        "new_mean_ms": 235.41379310344828,
        "old_std_ms": 1.081642611455487,
        "new_std_ms": 1.6150462483274053,
        "effect_size_cohens_d": 0.2759688234745103,
        "old_ci95_ms": [
          235.38166860282038,
          236.20453829373128
        ],
        "new_ci95_ms": [
          234.79946236559965,
          236.02812384129692
        ],
        "old_ci99_ms": [
          235.2380856307149,
          236.3481212658368
        ],
        "new_ci99_ms": [
          234.58507256811316,
          236.2425136387834
        ],
        "new_times": [
          0.233,
          0.234,
          0.234,
          0.238,
          0.237,
          0.238,
          0.234,
          0.235,
          0.237,
          0.235,
          0.236,
          0.234,
          0.233,
          0.235,
          0.234,
          0.235,
          0.234,
          0.235,
          0.238,
          0.238,
          0.235,
          0.237,
          0.235,
          0.238,
          0.235,
          0.237,
          0.234,
          0.234,
          0.235
        ],
        "old_times": [
          0.236,
          0.237,
          0.235,
          0.234,
          0.236,
          0.237,
          0.236,
          0.235,
          0.237,
          0.237,
          0.237,
          0.237,
          0.235,
          0.236,
          0.235,
          0.236,
          0.237,
          0.235,
          0.236,
          0.236,
          0.237,
          0.234,
          0.235,
          0.235,
          0.237,
          0.236,
          0.233,
          0.236,
          0.235
        ]
      },
      {
        "test_name": "[power]<xsimd::batch<double>>",
        "is_significant": false,
        "p_value": 1.0,
        "is_pair_significant": false,
        "pair_p_value": 0.9999999999999964,
        "is_binom_significant": false,
        "binom_p_value": 1.0,
        "is_wilcoxon_significant": false,
        "wilcoxon_p_value": 0.9999987668720761,
        "is_mannwhitney_significant": false,
        "mannwhitney_p_value": 0.3277764652246413,
        "relative_improvement": -0.0010857763300760053,
        "absolute_improvement_ms": -0.27586206896551557,
        "old_mean_ms": 254.0689655172414,
        "new_mean_ms": 254.34482758620692,
        "old_std_ms": 4.131162362223763,
        "new_std_ms": 2.022654939658793,
        "effect_size_cohens_d": -0.0848151475205112,
        "old_ci95_ms": [
          252.49755539521806,
          255.64037563926473
        ],
        "new_ci95_ms": [
          253.57545079419202,
          255.11420437822179
        ],
        "old_ci99_ms": [
          251.9491630113231,
          256.1887680231597
        ],
        "new_ci99_ms": [
          253.30695285901055,
          255.38270231340326
        ],
        "new_times": [
          0.255,
          0.256,
          0.253,
          0.256,
          0.256,
          0.254,
          0.252,
          0.254,
          0.253,
          0.255,
          0.253,
          0.257,
          0.256,
          0.255,
          0.253,
          0.252,
          0.251,
          0.258,
          0.255,
          0.254,
          0.254,
          0.252,
          0.256,
          0.257,
          0.255,
          0.258,
          0.251,
          0.254,
          0.251
        ],
        "old_times": [
          0.256,
          0.249,
          0.248,
          0.251,
          0.248,
          0.257,
          0.255,
          0.249,
          0.256,
          0.249,
          0.256,
          0.251,
          0.259,
          0.256,
          0.249,
          0.259,
          0.259,
          0.258,
          0.256,
          0.259,
          0.248,
          0.258,
          0.256,
          0.258,
          0.258,
          0.254,
          0.257,
          0.251,
          0.248
        ]
      },
      {
        "test_name": "[select]<xsimd::batch<unsigned char>>",
        "is_significant": false,
        "p_value": 1.0,
        "is_pair_significant": false,
        "pair_p_value": 1.0,
        "is_binom_significant": false,
        "binom_p_value": 1.0,
        "is_wilcoxon_significant": false,
        "wilcoxon_p_value": 0.9999994573316361,
        "is_mannwhitney_significant": false,
        "mannwhitney_p_value": 0.9999996072712385,
        "relative_improvement": -0.017716535433070883,
        "absolute_improvement_ms": -0.62068965517241,
        "old_mean_ms": 35.0344827586207,
        "new_mean_ms": 35.65517241379311,
        "old_std_ms": 0.1856953381770507,
        "new_std_ms": 0.4837252813149716,
        "effect_size_cohens_d": -1.6941008987392523,
        "old_ci95_ms": [
          34.96384802959328,
          35.10511748764812
        ],
        "new_ci95_ms": [
          35.471173157243015,
          35.839171670343205
        ],
        "old_ci99_ms": [
          34.93919784636342,
          35.129767670877975
        ],
        "new_ci99_ms": [
          35.40696090003514,
          35.90338392755108
        ],
        "new_times": [
          0.035,
          0.036,
          0.036,
          0.036,
          0.036,
          0.036,
          0.036,
          0.036,
          0.036,
          0.035,
          0.036,
          0.036,
          0.036,
          0.035,
          0.035,
          0.036,
          0.035,
          0.035,
          0.035,
          0.035,
          0.036,
          0.036,
          0.036,
          0.036,
          0.036,
          0.035,
          0.036,
          0.036,
          0.035
        ],
        "old_times": [
          0.035,
          0.035,
          0.035,
          0.035,
          0.035,
          0.035,
          0.035,
          0.036,
          0.035,
          0.035,
          0.035,
          0.035,
          0.035,
          0.035,
          0.035,
          0.035,
          0.035,
          0.035,
          0.035,
          0.035,
          0.035,
          0.035,
          0.035,
          0.035,
          0.035,
          0.035,
          0.035,
          0.035,
          0.035
        ]
      },
      {
        "test_name": "[select]<xsimd::batch<signed char>>",
        "is_significant": false,
        "p_value": 1.0,
        "is_pair_significant": false,
        "pair_p_value": 1.0,
        "is_binom_significant": false,
        "binom_p_value": 1.0,
        "is_wilcoxon_significant": false,
        "wilcoxon_p_value": 0.9999995043511859,
        "is_mannwhitney_significant": false,
        "mannwhitney_p_value": 0.9999999351309826,
        "relative_improvement": -0.01964839710444676,
        "absolute_improvement_ms": -0.6551724137931064,
        "old_mean_ms": 33.344827586206904,
        "new_mean_ms": 34.00000000000001,
        "old_std_ms": 0.48372528131497494,
        "new_std_ms": 7.061715720500897e-15,
        "effect_size_cohens_d": -1.9154543892354643,
        "old_ci95_ms": [
          33.1608283296568,
          33.528826842757
        ],
        "new_ci95_ms": [
          34.00000000000001,
          34.00000000000001
        ],
        "old_ci99_ms": [
          33.09661607244893,
          33.59303909996488
        ],
        "new_ci99_ms": [
          34.0,
          34.000000000000014
        ],
        "new_times": [
          0.034,
          0.034,
          0.034,
          0.034,
          0.034,
          0.034,
          0.034,
          0.034,
          0.034,
          0.034,
          0.034,
          0.034,
          0.034,
          0.034,
          0.034,
          0.034,
          0.034,
          0.034,
          0.034,
          0.034,
          0.034,
          0.034,
          0.034,
          0.034,
          0.034,
          0.034,
          0.034,
          0.034,
          0.034
        ],
        "old_times": [
          0.034,
          0.033,
          0.033,
          0.033,
          0.033,
          0.033,
          0.033,
          0.034,
          0.034,
          0.033,
          0.033,
          0.033,
          0.033,
          0.033,
          0.033,
          0.034,
          0.034,
          0.034,
          0.033,
          0.033,
          0.033,
          0.033,
          0.034,
          0.034,
          0.034,
          0.033,
          0.034,
          0.033,
          0.033
        ]
      },
      {
        "test_name": "[select]<xsimd::batch<short unsigned int>>",
        "is_significant": false,
        "p_value": 0.999999999996027,
        "is_pair_significant": false,
        "pair_p_value": 0.9999999999567667,
        "is_binom_significant": false,
        "binom_p_value": 1.0,
        "is_wilcoxon_significant": false,
        "wilcoxon_p_value": 0.9999995453596235,
        "is_mannwhitney_significant": false,
        "mannwhitney_p_value": 0.014842546117879317,
        "relative_improvement": 0.010101010101010109,
        "absolute_improvement_ms": 0.24137931034482613,
        "old_mean_ms": 23.896551724137936,
        "new_mean_ms": 23.65517241379311,
        "old_std_ms": 0.30993404669460367,
        "new_std_ms": 0.483725281314975,
        "effect_size_cohens_d": 0.5941904365039276,
        "old_ci95_ms": [
          23.77865911778843,
          24.014444330487443
        ],
        "new_ci95_ms": [
          23.471173157243012,
          23.83917167034321
        ],
        "old_ci99_ms": [
          23.73751683002185,
          24.055586618254022
        ],
        "new_ci99_ms": [
          23.406960900035138,
          23.903383927551083
        ],
        "new_times": [
          0.024,
          0.024,
          0.023,
          0.023,
          0.024,
          0.024,
          0.024,
          0.024,
          0.024,
          0.023,
          0.024,
          0.023,
          0.024,
          0.024,
          0.024,
          0.023,
          0.024,
          0.024,
          0.023,
          0.023,
          0.023,
          0.023,
          0.024,
          0.023,
          0.024,
          0.024,
          0.024,
          0.024,
          0.024
        ],
        "old_times": [
          0.024,
          0.024,
          0.024,
          0.023,
          0.024,
          0.024,
          0.024,
          0.024,
          0.024,
          0.024,
          0.024,
          0.023,
          0.024,
          0.024,
          0.024,
          0.024,
          0.024,
          0.024,
          0.024,
          0.024,
          0.024,
          0.024,
          0.024,
          0.024,
          0.023,
          0.024,
          0.024,
          0.024,
          0.024
        ]
      },
      {
        "test_name": "[select]<xsimd::batch<short int>>",
        "is_significant": false,
        "p_value": 1.0,
        "is_pair_significant": false,
        "pair_p_value": 1.0,
        "is_binom_significant": false,
        "binom_p_value": 1.0,
        "is_wilcoxon_significant": false,
        "wilcoxon_p_value": 0.9999998379079917,
        "is_mannwhitney_significant": false,
        "mannwhitney_p_value": 0.9576857456395491,
        "relative_improvement": -0.006259780907668237,
        "absolute_improvement_ms": -0.13793103448275779,
        "old_mean_ms": 22.034482758620694,
        "new_mean_ms": 22.172413793103452,
        "old_std_ms": 0.18569533817705197,
        "new_std_ms": 0.384425872219245,
        "effect_size_cohens_d": -0.45690314577878627,
        "old_ci95_ms": [
          21.963848029593272,
          22.105117487648116
        ],
        "new_ci95_ms": [
          22.02618601171754,
          22.318641574489362
        ],
        "old_ci99_ms": [
          21.939197846363417,
          22.12976767087797
        ],
        "new_ci99_ms": [
          21.975155284282337,
          22.36967230192457
        ],
        "new_times": [
          0.022,
          0.022,
          0.022,
          0.022,
          0.022,
          0.022,
          0.022,
          0.022,
          0.022,
          0.022,
          0.022,
          0.022,
          0.022,
          0.022,
          0.022,
          0.022,
          0.022,
          0.023,
          0.022,
          0.023,
          0.023,
          0.023,
          0.023,
          0.022,
          0.022,
          0.022,
          0.022,
          0.022,
          0.022
        ],
        "old_times": [
          0.022,
          0.022,
          0.022,
          0.022,
          0.022,
          0.022,
          0.022,
          0.022,
          0.022,
          0.022,
          0.022,
          0.022,
          0.022,
          0.022,
          0.022,
          0.022,
          0.022,
          0.022,
          0.022,
          0.022,
          0.023,
          0.022,
          0.022,
          0.022,
          0.022,
          0.022,
          0.022,
          0.022,
          0.022
        ]
      },
      {
        "test_name": "[select]<xsimd::batch<unsigned int>>",
        "is_significant": false,
        "p_value": 0.9999999999972619,
        "is_pair_significant": false,
        "pair_p_value": 0.9999999999151837,
        "is_binom_significant": false,
        "binom_p_value": 0.9999991878867149,
        "is_wilcoxon_significant": false,
        "wilcoxon_p_value": 0.9999995593496304,
        "is_mannwhitney_significant": false,
        "mannwhitney_p_value": 0.36537939133487474,
        "relative_improvement": 0.0021645021645021662,
        "absolute_improvement_ms": 0.034482758620692916,
        "old_mean_ms": 15.931034482758625,
        "new_mean_ms": 15.896551724137932,
        "old_std_ms": 0.3713906763541041,
        "new_std_ms": 0.3099340466946037,
        "effect_size_cohens_d": 0.10081338890713876,
        "old_ci95_ms": [
          15.789765024703781,
          16.07230394081347
        ],
        "new_ci95_ms": [
          15.778659117788425,
          16.01444433048744
        ],
        "old_ci99_ms": [
          15.74046465824407,
          16.12160430727318
        ],
        "new_ci99_ms": [
          15.737516830021846,
          16.05558661825402
        ],
        "new_times": [
          0.016,
          0.016,
          0.016,
          0.016,
          0.016,
          0.016,
          0.016,
          0.016,
          0.016,
          0.016,
          0.016,
          0.016,
          0.015,
          0.016,
          0.015,
          0.016,
          0.016,
          0.016,
          0.016,
          0.016,
          0.016,
          0.016,
          0.016,
          0.016,
          0.016,
          0.016,
          0.015,
          0.016,
          0.016
        ],
        "old_times": [
          0.016,
          0.016,
          0.016,
          0.016,
          0.016,
          0.016,
          0.016,
          0.015,
          0.016,
          0.016,
          0.016,
          0.016,
          0.015,
          0.015,
          0.016,
          0.016,
          0.016,
          0.016,
          0.016,
          0.016,
          0.016,
          0.017,
          0.016,
          0.016,
          0.016,
          0.016,
          0.016,
          0.016,
          0.016
        ]
      },
      {
        "test_name": "[select]<xsimd::batch<int>>",
        "is_significant": false,
        "p_value": 0.9999999999783271,
        "is_pair_significant": false,
        "pair_p_value": 0.9999999999783271,
        "is_binom_significant": false,
        "binom_p_value": 0.9999991878867149,
        "is_wilcoxon_significant": false,
        "wilcoxon_p_value": 0.9999997462405394,
        "is_mannwhitney_significant": false,
        "mannwhitney_p_value": 0.04066732549977193,
        "relative_improvement": 0.00738916256157636,
        "absolute_improvement_ms": 0.10344827586206834,
        "old_mean_ms": 14.000000000000002,
        "new_mean_ms": 13.896551724137934,
        "old_std_ms": 1.7654289301252243e-15,
        "new_std_ms": 0.3099340466946037,
        "effect_size_cohens_d": 0.4720293116825797,
        "old_ci95_ms": [
          14.000000000000002,
          14.000000000000002
        ],
        "new_ci95_ms": [
          13.778659117788427,
          14.014444330487441
        ],
        "old_ci99_ms": [
          14.0,
          14.000000000000004
        ],
        "new_ci99_ms": [
          13.737516830021846,
          14.05558661825402
        ],
        "new_times": [
          0.014,
          0.014,
          0.014,
          0.014,
          0.014,
          0.014,
          0.013,
          0.013,
          0.014,
          0.014,
          0.014,
          0.014,
          0.014,
          0.014,
          0.014,
          0.014,
          0.014,
          0.014,
          0.014,
          0.014,
          0.014,
          0.013,
          0.014,
          0.014,
          0.014,
          0.014,
          0.014,
          0.014,
          0.014
        ],
        "old_times": [
          0.014,
          0.014,
          0.014,
          0.014,
          0.014,
          0.014,
          0.014,
          0.014,
          0.014,
          0.014,
          0.014,
          0.014,
          0.014,
          0.014,
          0.014,
          0.014,
          0.014,
          0.014,
          0.014,
          0.014,
          0.014,
          0.014,
          0.014,
          0.014,
          0.014,
          0.014,
          0.014,
          0.014,
          0.014
        ]
      },
      {
        "test_name": "[select]<xsimd::batch<long unsigned int>>",
        "is_significant": false,
        "p_value": 0.9999957282391886,
        "is_pair_significant": false,
        "pair_p_value": 0.9999841263035039,
        "is_binom_significant": false,
        "binom_p_value": 0.9997269436717033,
        "is_wilcoxon_significant": false,
        "wilcoxon_p_value": 0.9999958884558122,
        "is_mannwhitney_significant": false,
        "mannwhitney_p_value": 0.08588757855908224,
        "relative_improvement": 0.011267605633802828,
        "absolute_improvement_ms": 0.1379310344827595,
        "old_mean_ms": 12.241379310344831,
        "new_mean_ms": 12.103448275862071,
        "old_std_ms": 0.43549417035569243,
        "new_std_ms": 0.3099340466946031,
        "effect_size_cohens_d": 0.36493121531925654,
        "old_ci95_ms": [
          12.075726187234292,
          12.40703243345537
        ],
        "new_ci95_ms": [
          11.985555669512566,
          12.221340882211578
        ],
        "old_ci99_ms": [
          12.017916383282365,
          12.464842237407296
        ],
        "new_ci99_ms": [
          11.944413381745985,
          12.26248316997816
        ],
        "new_times": [
          0.012,
          0.012,
          0.012,
          0.012,
          0.012,
          0.012,
          0.012,
          0.013,
          0.012,
          0.012,
          0.012,
          0.012,
          0.012,
          0.012,
          0.012,
          0.013,
          0.012,
          0.012,
          0.012,
          0.013,
          0.012,
          0.012,
          0.012,
          0.012,
          0.012,
          0.012,
          0.012,
          0.012,
          0.012
        ],
        "old_times": [
          0.013,
          0.012,
          0.012,
          0.012,
          0.012,
          0.012,
          0.013,
          0.013,
          0.012,
          0.012,
          0.013,
          0.013,
          0.012,
          0.012,
          0.012,
          0.012,
          0.012,
          0.012,
          0.012,
          0.012,
          0.012,
          0.012,
          0.012,
          0.012,
          0.013,
          0.013,
          0.012,
          0.012,
          0.012
        ]
      },
      {
        "test_name": "[select]<xsimd::batch<long int>>",
        "is_significant": false,
        "p_value": 1.0,
        "is_pair_significant": false,
        "pair_p_value": 1.0,
        "is_binom_significant": false,
        "binom_p_value": 1.0,
        "is_wilcoxon_significant": false,
        "wilcoxon_p_value": 0.9999999638108507,
        "is_mannwhitney_significant": false,
        "mannwhitney_p_value": 1.0,
        "relative_improvement": 0.0,
        "absolute_improvement_ms": 0.0,
        "old_mean_ms": 11.000000000000004,
        "new_mean_ms": 11.000000000000004,
        "old_std_ms": 3.5308578602504487e-15,
        "new_std_ms": 3.5308578602504487e-15,
        "effect_size_cohens_d": 0.0,
        "old_ci95_ms": [
          11.000000000000002,
          11.000000000000005
        ],
        "new_ci95_ms": [
          11.000000000000002,
          11.000000000000005
        ],
        "old_ci99_ms": [
          11.000000000000002,
          11.000000000000005
        ],
        "new_ci99_ms": [
          11.000000000000002,
          11.000000000000005
        ],
        "new_times": [
          0.011,
          0.011,
          0.011,
          0.011,
          0.011,
          0.011,
          0.011,
          0.011,
          0.011,
          0.011,
          0.011,
          0.011,
          0.011,
          0.011,
          0.011,
          0.011,
          0.011,
          0.011,
          0.011,
          0.011,
          0.011,
          0.011,
          0.011,
          0.011,
          0.011,
          0.011,
          0.011,
          0.011,
          0.011
        ],
        "old_times": [
          0.011,
          0.011,
          0.011,
          0.011,
          0.011,
          0.011,
          0.011,
          0.011,
          0.011,
          0.011,
          0.011,
          0.011,
          0.011,
          0.011,
          0.011,
          0.011,
          0.011,
          0.011,
          0.011,
          0.011,
          0.011,
          0.011,
          0.011,
          0.011,
          0.011,
          0.011,
          0.011,
          0.011,
          0.011
        ]
      },
      {
        "test_name": "[select]<xsimd::batch<float>>",
        "is_significant": false,
        "p_value": 0.9999999999999998,
        "is_pair_significant": false,
        "pair_p_value": 0.9999999999999146,
        "is_binom_significant": false,
        "binom_p_value": 1.0,
        "is_wilcoxon_significant": false,
        "wilcoxon_p_value": 0.9999993896261342,
        "is_mannwhitney_significant": false,
        "mannwhitney_p_value": 0.9988649196318261,
        "relative_improvement": -0.017182130584192455,
        "absolute_improvement_ms": -0.34482758620689447,
        "old_mean_ms": 20.068965517241384,
        "new_mean_ms": 20.413793103448278,
        "old_std_ms": 0.257880714777564,
        "new_std_ms": 0.5012300141587658,
        "effect_size_cohens_d": -0.8651375484935377,
        "old_ci95_ms": [
          19.97087293942802,
          20.167058095054745
        ],
        "new_ci95_ms": [
          20.22313540262458,
          20.604450804271973
        ],
        "old_ci99_ms": [
          19.936640486782107,
          20.20129054770066
        ],
        "new_ci99_ms": [
          20.156599474417614,
          20.67098673247894
        ],
        "new_times": [
          0.02,
          0.02,
          0.02,
          0.02,
          0.02,
          0.021,
          0.021,
          0.021,
          0.021,
          0.021,
          0.021,
          0.02,
          0.02,
          0.021,
          0.02,
          0.02,
          0.02,
          0.021,
          0.021,
          0.021,
          0.02,
          0.02,
          0.021,
          0.02,
          0.02,
          0.02,
          0.02,
          0.02,
          0.021
        ],
        "old_times": [
          0.02,
          0.02,
          0.02,
          0.02,
          0.02,
          0.02,
          0.02,
          0.02,
          0.02,
          0.02,
          0.02,
          0.02,
          0.02,
          0.02,
          0.02,
          0.02,
          0.021,
          0.021,
          0.02,
          0.02,
          0.02,
          0.02,
          0.02,
          0.02,
          0.02,
          0.02,
          0.02,
          0.02,
          0.02
        ]
      },
      {
        "test_name": "[select]<xsimd::batch<double>>",
        "is_significant": false,
        "p_value": 0.9999753623526433,
        "is_pair_significant": false,
        "pair_p_value": 0.9999866853858661,
        "is_binom_significant": false,
        "binom_p_value": 0.995934970676899,
        "is_wilcoxon_significant": false,
        "wilcoxon_p_value": 0.9999745829072498,
        "is_mannwhitney_significant": false,
        "mannwhitney_p_value": 0.09591346022343977,
        "relative_improvement": 0.011764705882352951,
        "absolute_improvement_ms": 0.17241379310344895,
        "old_mean_ms": 14.655172413793105,
        "new_mean_ms": 14.482758620689657,
        "old_std_ms": 0.4837252813149741,
        "new_std_ms": 0.5085476277156074,
        "effect_size_cohens_d": 0.3474041668898273,
        "old_ci95_ms": [
          14.471173157243005,
          14.839171670343205
        ],
        "new_ci95_ms": [
          14.289317448531735,
          14.676199792847576
        ],
        "old_ci99_ms": [
          14.406960900035132,
          14.903383927551078
        ],
        "new_ci99_ms": [
          14.221810141523598,
          14.743707099855714
        ],
        "new_times": [
          0.014,
          0.014,
          0.014,
          0.014,
          0.015,
          0.014,
          0.014,
          0.014,
          0.014,
          0.015,
          0.015,
          0.014,
          0.015,
          0.015,
          0.014,
          0.014,
          0.015,
          0.015,
          0.014,
          0.015,
          0.015,
          0.015,
          0.015,
          0.015,
          0.014,
          0.014,
          0.015,
          0.015,
          0.014
        ],
        "old_times": [
          0.015,
          0.014,
          0.014,
          0.015,
          0.015,
          0.015,
          0.014,
          0.014,
          0.014,
          0.014,
          0.015,
          0.015,
          0.015,
          0.015,
          0.015,
          0.015,
          0.014,
          0.015,
          0.014,
          0.015,
          0.015,
          0.014,
          0.015,
          0.015,
          0.014,
          0.015,
          0.015,
          0.015,
          0.015
        ]
      },
      {
        "test_name": "[trigonometric]<xsimd::batch<float>>",
        "is_significant": false,
        "p_value": 1.0,
        "is_pair_significant": false,
        "pair_p_value": 1.0,
        "is_binom_significant": false,
        "binom_p_value": 1.0,
        "is_wilcoxon_significant": false,
        "wilcoxon_p_value": 0.9999990925831485,
        "is_mannwhitney_significant": false,
        "mannwhitney_p_value": 0.0008163641791398739,
        "relative_improvement": 0.002667615152054007,
        "absolute_improvement_ms": 0.517241379310418,
        "old_mean_ms": 193.89655172413794,
        "new_mean_ms": 193.37931034482753,
        "old_std_ms": 0.557086014531156,
        "new_std_ms": 0.6768515929047775,
        "effect_size_cohens_d": 0.8344378180240498,
        "old_ci95_ms": [
          193.68464753705567,
          194.10845591122023
        ],
        "new_ci95_ms": [
          193.12184976813268,
          193.63677092152238
        ],
        "old_ci99_ms": [
          193.6106969873661,
          194.1824064609098
        ],
        "new_ci99_ms": [
          193.0320009009058,
          193.72661978874925
        ],
        "new_times": [
          0.194,
          0.195,
          0.193,
          0.193,
          0.193,
          0.194,
          0.195,
          0.193,
          0.194,
          0.194,
          0.193,
          0.193,
          0.194,
          0.193,
          0.194,
          0.193,
          0.193,
          0.193,
          0.193,
          0.193,
          0.194,
          0.194,
          0.192,
          0.193,
          0.193,
          0.193,
          0.193,
          0.193,
          0.193
        ],
        "old_times": [
          0.193,
          0.194,
          0.194,
          0.194,
          0.194,
          0.194,
          0.194,
          0.194,
          0.194,
          0.194,
          0.194,
          0.193,
          0.194,
          0.194,
          0.194,
          0.194,
          0.193,
          0.195,
          0.194,
          0.194,
          0.194,
          0.193,
          0.193,
          0.195,
          0.193,
          0.194,
          0.195,
          0.194,
          0.194
        ]
      },
      {
        "test_name": "[trigonometric]<xsimd::batch<double>>",
        "is_significant": false,
        "p_value": 1.0,
        "is_pair_significant": false,
        "pair_p_value": 1.0,
        "is_binom_significant": false,
        "binom_p_value": 1.0,
        "is_wilcoxon_significant": false,
        "wilcoxon_p_value": 0.9999987818413122,
        "is_mannwhitney_significant": false,
        "mannwhitney_p_value": 0.4651576254162372,
        "relative_improvement": -0.0012551551013090482,
        "absolute_improvement_ms": -0.2413793103448192,
        "old_mean_ms": 192.31034482758625,
        "new_mean_ms": 192.55172413793107,
        "old_std_ms": 2.1729415263295286,
        "new_std_ms": 0.9481638984506449,
        "effect_size_cohens_d": -0.14398598996322257,
        "old_ci95_ms": [
          191.48380207529388,
          193.1368875798786
        ],
        "new_ci95_ms": [
          192.19106187953452,
          192.9123863963276
        ],
        "old_ci99_ms": [
          191.19535430219625,
          193.42533535297625
        ],
        "new_ci99_ms": [
          192.0651975791262,
          193.03825069673593
        ],
        "new_times": [
          0.193,
          0.193,
          0.194,
          0.193,
          0.192,
          0.192,
          0.192,
          0.192,
          0.191,
          0.193,
          0.194,
          0.194,
          0.193,
          0.194,
          0.192,
          0.192,
          0.191,
          0.194,
          0.192,
          0.193,
          0.192,
          0.192,
          0.192,
          0.191,
          0.192,
          0.192,
          0.192,
          0.194,
          0.193
        ],
        "old_times": [
          0.192,
          0.194,
          0.195,
          0.195,
          0.19,
          0.19,
          0.19,
          0.195,
          0.194,
          0.191,
          0.195,
          0.194,
          0.192,
          0.193,
          0.192,
          0.191,
          0.192,
          0.189,
          0.194,
          0.193,
          0.189,
          0.194,
          0.189,
          0.193,
          0.194,
          0.194,
          0.195,
          0.189,
          0.189
        ]
      }
    ]
  },
  "logs": {
    "full_log_path": "/logs/full.log",
    "config_log_path": "/logs/config.log",
    "build_log_path": "/logs/build.log",
    "test_log_path": "/logs/test.log",
    "build_success": true,
    "test_success": true
  },
  "raw_timing_data": {
    "warmup_runs": 1,
    "measurement_runs": 30,
    "min_exec_time_improvement": 0.05,
    "min_p_value": 0.05
  }
}